Workbook

Sheet Overview
A1: Cult & Forgotten Cinema Preservation Master Index | F1: =HYPERLINK("#'SEARCH'!A1","🔍 SEARCH") -> 🔍 SEARCH | G1: =HYPERLINK("#'GUIDE'!A1","📚 GUIDE") -> 📚 GUIDE
A2: Pre-1960 foundations + 1960–1999 · 2.062 preservation leads | H2: Tracker v2
H3: Status | I3: ☐ / ☑
A4: Year | B4: Titles | C4: A priority | D4: B priority | E4: C priority | F4: Notes | H4: Per jaar | I4: live counter onderaan
A5: 1960 | B5: =COUNTA('1960'!A2:A500) -> 11 | C5: =COUNTIF('1960'!B2:B500,"A") -> 4 | D5: =COUNTIF('1960'!B2:B500,"B") -> 5 | E5: =COUNTIF('1960'!B2:B500,"C") -> 2 | H5: Genre | I5: vervangt oude tags
A6: 1961 | B6: =COUNTA('1961'!A2:A500) -> 8 | C6: =COUNTIF('1961'!B2:B500,"A") -> 4 | D6: =COUNTIF('1961'!B2:B500,"B") -> 3 | E6: =COUNTIF('1961'!B2:B500,"C") -> 1 | H6: Titelnotitie | I6: klik/hover op titel
A7: 1962 | B7: =COUNTA('1962'!A2:A500) -> 9 | C7: =COUNTIF('1962'!B2:B500,"A") -> 5 | D7: =COUNTIF('1962'!B2:B500,"B") -> 3 | E7: =COUNTIF('1962'!B2:B500,"C") -> 1
A8: 1963 | B8: =COUNTA('1963'!A2:A500) -> 11 | C8: =COUNTIF('1963'!B2:B500,"A") -> 7 | D8: =COUNTIF('1963'!B2:B500,"B") -> 3 | E8: =COUNTIF('1963'!B2:B500,"C") -> 1 | H8: Genre expansion v3
A9: 1964 | B9: =COUNTA('1964'!A2:A500) -> 16 | C9: =COUNTIF('1964'!B2:B500,"A") -> 13 | D9: =COUNTIF('1964'!B2:B500,"B") -> 2 | E9: =COUNTIF('1964'!B2:B500,"C") -> 1 | H9: Focus | I9: Music / Dance / Disco / Rock / Pop
A10: 1965 | B10: =COUNTA('1965'!A2:A500) -> 13 | C10: =COUNTIF('1965'!B2:B500,"A") -> 10 | D10: =COUNTIF('1965'!B2:B500,"B") -> 3 | E10: =COUNTIF('1965'!B2:B500,"C") -> 0 | H10: Nieuwe titels | I10: 60
A11: 1966 | B11: =COUNTA('1966'!A2:A500) -> 18 | C11: =COUNTIF('1966'!B2:B500,"A") -> 13 | D11: =COUNTIF('1966'!B2:B500,"B") -> 3 | E11: =COUNTIF('1966'!B2:B500,"C") -> 2 | H11: Dubbele titels overgeslagen | I11: 10
A12: 1967 | B12: =COUNTA('1967'!A2:A500) -> 16 | C12: =COUNTIF('1967'!B2:B500,"A") -> 13 | D12: =COUNTIF('1967'!B2:B500,"B") -> 3 | E12: =COUNTIF('1967'!B2:B500,"C") -> 0 | H12: Research anchors | I12: BFI / TCM
A13: 1968 | B13: =COUNTA('1968'!A2:A500) -> 23 | C13: =COUNTIF('1968'!B2:B500,"A") -> 19 | D13: =COUNTIF('1968'!B2:B500,"B") -> 2 | E13: =COUNTIF('1968'!B2:B500,"C") -> 2 | H13: Voorbeelden | I13: Grease · Saturday Night Fever · Fame · Flashdance
A14: 1969 | B14: =COUNTA('1969'!A2:A500) -> 14 | C14: =COUNTIF('1969'!B2:B500,"A") -> 9 | D14: =COUNTIF('1969'!B2:B500,"B") -> 5 | E14: =COUNTIF('1969'!B2:B500,"C") -> 0
A15: 1970 | B15: =COUNTA('1970'!A2:A500) -> 64 | C15: =COUNTIF('1970'!B2:B500,"A") -> 17 | D15: =COUNTIF('1970'!B2:B500,"B") -> 46 | E15: =COUNTIF('1970'!B2:B500,"C") -> 1 | H15: Expansion v4
A16: 1971 | B16: =COUNTA('1971'!A2:A500) -> 74 | C16: =COUNTIF('1971'!B2:B500,"A") -> 16 | D16: =COUNTIF('1971'!B2:B500,"B") -> 53 | E16: =COUNTIF('1971'!B2:B500,"C") -> 5 | H16: New focus | I16: Teen / High-Concept | J16: Spoof / Slapstick | K16: Blaxploitation / Black Cult
A17: 1972 | B17: =COUNTA('1972'!A2:A500) -> 72 | C17: =COUNTIF('1972'!B2:B500,"A") -> 28 | D17: =COUNTIF('1972'!B2:B500,"B") -> 41 | E17: =COUNTIF('1972'!B2:B500,"C") -> 3 | H17: Core tags | I17: Teen Sci-Fi Comedy | J17: Spoof / Parody | K17: Blaxploitation
A18: 1973 | B18: =COUNTA('1973'!A2:A500) -> 77 | C18: =COUNTIF('1973'!B2:B500,"A") -> 23 | D18: =COUNTIF('1973'!B2:B500,"B") -> 52 | E18: =COUNTIF('1973'!B2:B500,"C") -> 2 | I18: Body-Swap Comedy | J18: Broad Comedy | K18: Black Comedy
A19: 1974 | B19: =COUNTA('1974'!A2:A500) -> 66 | C19: =COUNTIF('1974'!B2:B500,"A") -> 27 | D19: =COUNTIF('1974'!B2:B500,"B") -> 37 | E19: =COUNTIF('1974'!B2:B500,"C") -> 2 | I19: Fantasy Comedy | J19: Road / Buddy Comedy | K19: Black Cinema
A20: 1975 | B20: =COUNTA('1975'!A2:A500) -> 53 | C20: =COUNTIF('1975'!B2:B500,"A") -> 27 | D20: =COUNTIF('1975'!B2:B500,"B") -> 25 | E20: =COUNTIF('1975'!B2:B500,"C") -> 1 | I20: Geek / Nerd Comedy | J20: Dark Comedy | K20: Black Horror
A21: 1976 | B21: =COUNTA('1976'!A2:A500) -> 63 | C21: =COUNTIF('1976'!B2:B500,"A") -> 24 | D21: =COUNTIF('1976'!B2:B500,"B") -> 37 | E21: =COUNTIF('1976'!B2:B500,"C") -> 2 | I21: Youth Adventure | J21: Institution Comedy | K21: Black Music / Cult
A22: 1977 | B22: =COUNTA('1977'!A2:A500) -> 55 | C22: =COUNTIF('1977'!B2:B500,"A") -> 24 | D22: =COUNTIF('1977'!B2:B500,"B") -> 31 | E22: =COUNTIF('1977'!B2:B500,"C") -> 0
A23: 1978 | B23: =COUNTA('1978'!A2:A500) -> 68 | C23: =COUNTIF('1978'!B2:B500,"A") -> 31 | D23: =COUNTIF('1978'!B2:B500,"B") -> 35 | E23: =COUNTIF('1978'!B2:B500,"C") -> 2 | H23: New films | I23: 169 | J23: Already present | K23: 36
A24: 1979 | B24: =COUNTA('1979'!A2:A500) -> 54 | C24: =COUNTIF('1979'!B2:B500,"A") -> 24 | D24: =COUNTIF('1979'!B2:B500,"B") -> 26 | E24: =COUNTIF('1979'!B2:B500,"C") -> 4 | H24: Research anchor | I24: BFI comedy
A25: 1980 | B25: =COUNTA('1980'!A2:A500) -> 63 | C25: =COUNTIF('1980'!B2:B500,"A") -> 40 | D25: =COUNTIF('1980'!B2:B500,"B") -> 23 | E25: =COUNTIF('1980'!B2:B500,"C") -> 0 | H25: Research anchor | I25: BFI blaxploitation
A26: 1981 | B26: =COUNTA('1981'!A2:A500) -> 90 | C26: =COUNTIF('1981'!B2:B500,"A") -> 36 | D26: =COUNTIF('1981'!B2:B500,"B") -> 54 | E26: =COUNTIF('1981'!B2:B500,"C") -> 0
A27: 1982 | B27: =COUNTA('1982'!A2:A500) -> 84 | C27: =COUNTIF('1982'!B2:B500,"A") -> 44 | D27: =COUNTIF('1982'!B2:B500,"B") -> 35 | E27: =COUNTIF('1982'!B2:B500,"C") -> 5 | H27: Examples | I27: Weird Science | J27: Airplane! | K27: Shaft
A28: 1983 | B28: =COUNTA('1983'!A2:A500) -> 74 | C28: =COUNTIF('1983'!B2:B500,"A") -> 47 | D28: =COUNTIF('1983'!B2:B500,"B") -> 26 | E28: =COUNTIF('1983'!B2:B500,"C") -> 1 | I28: Real Genius | J28: The Naked Gun | K28: Coffy
A29: 1984 | B29: =COUNTA('1984'!A2:A500) -> 69 | C29: =COUNTIF('1984'!B2:B500,"A") -> 40 | D29: =COUNTIF('1984'!B2:B500,"B") -> 28 | E29: =COUNTIF('1984'!B2:B500,"C") -> 1 | I29: Teen Witch | J29: Police Academy | K29: I'm Gonna Git You Sucka
A30: 1985 | B30: =COUNTA('1985'!A2:A500) -> 98 | C30: =COUNTIF('1985'!B2:B500,"A") -> 56 | D30: =COUNTIF('1985'!B2:B500,"B") -> 40 | E30: =COUNTIF('1985'!B2:B500,"C") -> 2
A31: 1986 | B31: =COUNTA('1986'!A2:A500) -> 84 | C31: =COUNTIF('1986'!B2:B500,"A") -> 50 | D31: =COUNTIF('1986'!B2:B500,"B") -> 32 | E31: =COUNTIF('1986'!B2:B500,"C") -> 2 | H31: Expansion v5
A32: 1987 | B32: =COUNTA('1987'!A2:A500) -> 89 | C32: =COUNTIF('1987'!B2:B500,"A") -> 48 | D32: =COUNTIF('1987'!B2:B500,"B") -> 36 | E32: =COUNTIF('1987'!B2:B500,"C") -> 5 | H32: Focus | I32: Post-Apocalyptic | J32: Road Warrior / Mad Max clones | K32: Wasteland / Dystopian DTV
A33: 1988 | B33: =COUNTA('1988'!A2:A500) -> 57 | C33: =COUNTIF('1988'!B2:B500,"A") -> 47 | D33: =COUNTIF('1988'!B2:B500,"B") -> 7 | E33: =COUNTIF('1988'!B2:B500,"C") -> 3 | H33: New films | I33: 61 | J33: Existing reviewed | K33: 14
A34: 1989 | B34: =COUNTA('1989'!A2:A500) -> 48 | C34: =COUNTIF('1989'!B2:B500,"A") -> 40 | D34: =COUNTIF('1989'!B2:B500,"B") -> 5 | E34: =COUNTIF('1989'!B2:B500,"C") -> 3 | H34: Core cycle | I34: Italian post-nuke | J34: Philippine wasteland | K34: 80s/90s DTV
A35: 1990 | B35: =COUNTA('1990'!A2:A500) -> 50 | C35: =COUNTIF('1990'!B2:B500,"A") -> 42 | D35: =COUNTIF('1990'!B2:B500,"B") -> 6 | E35: =COUNTIF('1990'!B2:B500,"C") -> 2 | H35: Adjacent | I35: Arthouse nuclear aftermath | J35: Cyberpunk wasteland | K35: Youth / road dystopia
A36: 1991 | B36: =COUNTA('1991'!A2:A500) -> 46 | C36: =COUNTIF('1991'!B2:B500,"A") -> 39 | D36: =COUNTIF('1991'!B2:B500,"B") -> 6 | E36: =COUNTIF('1991'!B2:B500,"C") -> 1 | H36: Anchors | I36: Mad Max | J36: The Road Warrior | K36: Escape from New York
A37: 1992 | B37: =COUNTA('1992'!A2:A500) -> 48 | C37: =COUNTIF('1992'!B2:B500,"A") -> 46 | D37: =COUNTIF('1992'!B2:B500,"B") -> 2 | E37: =COUNTIF('1992'!B2:B500,"C") -> 0 | H37: Cult examples | I37: 2019: After the Fall of New York | J37: Wheels of Fire | K37: Neon City
A38: 1993 | B38: =COUNTA('1993'!A2:A500) -> 45 | C38: =COUNTIF('1993'!B2:B500,"A") -> 35 | D38: =COUNTIF('1993'!B2:B500,"B") -> 7 | E38: =COUNTIF('1993'!B2:B500,"C") -> 3 | I38: The New Barbarians | J38: Equalizer 2000 | K38: Six-String Samurai
A39: 1994 | B39: =COUNTA('1994'!A2:A500) -> 59 | C39: =COUNTIF('1994'!B2:B500,"A") -> 38 | D39: =COUNTIF('1994'!B2:B500,"B") -> 19 | E39: =COUNTIF('1994'!B2:B500,"C") -> 2 | H39: Research | I39: Mondo Digital / title-specific references
A40: 1995 | B40: =COUNTA('1995'!A2:A500) -> 65 | C40: =COUNTIF('1995'!B2:B500,"A") -> 48 | D40: =COUNTIF('1995'!B2:B500,"B") -> 13 | E40: =COUNTIF('1995'!B2:B500,"C") -> 4 | H40: Source sheet | I40: Post-Apoc Sources
A41: 1996 | B41: =COUNTA('1996'!A2:A500) -> 54 | C41: =COUNTIF('1996'!B2:B500,"A") -> 43 | D41: =COUNTIF('1996'!B2:B500,"B") -> 10 | E41: =COUNTIF('1996'!B2:B500,"C") -> 1 | H41: Priority rule | I41: A = hunt/preserve | J41: B = strong candidate | K41: C = mainstream reminder
A42: 1997 | B42: =COUNTA('1997'!A2:A500) -> 46 | C42: =COUNTIF('1997'!B2:B500,"A") -> 36 | D42: =COUNTIF('1997'!B2:B500,"B") -> 6 | E42: =COUNTIF('1997'!B2:B500,"C") -> 4
A43: 1998 | B43: =COUNTA('1998'!A2:A500) -> 35 | C43: =COUNTIF('1998'!B2:B500,"A") -> 23 | D43: =COUNTIF('1998'!B2:B500,"B") -> 11 | E43: =COUNTIF('1998'!B2:B500,"C") -> 1
A44: 1999 | B44: =COUNTA('1999'!A2:A500) -> 31 | C44: =COUNTIF('1999'!B2:B500,"A") -> 24 | D44: =COUNTIF('1999'!B2:B500,"B") -> 4 | E44: =COUNTIF('1999'!B2:B500,"C") -> 3 | H44: Expansion v6
A45: TOTAL | B45: =SUM(B5:B44) -> 2020 | C45: =SUM(C5:C44) -> 1160 | D45: =SUM(D5:D44) -> 785 | E45: =SUM(E5:E44) -> 75 | H45: Focus | I45: Ozploitation 1971–1989 | J45: Cult-first | K45: No automatic A for obscurity
H46: Added | I46: 36 | J46: Existing reclassified | K46: 10
H47: A means | I47: Real cult / key cycle film | J47: B means | K47: Historical/strong preservation
H48: C means | I48: Mainstream reminder/anchor
H49: Core | I49: Stone | J49: The Man from Hong Kong | K49: Long Weekend
I50: Patrick | J50: Thirst | K50: Roadgames
I51: Next of Kin | J51: Razorback | K51: Dead-End Drive-In
H52: Adjacent arthouse | I52: Wake in Fright | J52: Picnic at Hanging Rock | K52: The Last Wave
H53: Research | I53: BFI + NFSA
H54: Source sheet | I54: Ozploitation Sources
H57: Expansion v7
H58: Focus | I58: Surreal / Liminal | J58: Artificial Worlds | K58: Dream Logic
H59: Added | I59: 21 | J59: Existing reviewed | K59: 37
H60: Rule | I60: Cult/arthouse/oddity first | J60: Not a historical genre label | K60: Modern preservation tag
H61: Core | I61: Toys | J61: Brazil | K61: Cube
I62: Barton Fink | J62: Paperhouse | K62: Dark City
I63: Meet the Hollowheads | J63: Motorama | K63: Institute Benjamenta
H64: Sub-tags | I64: Artificial World | J64: Institutional Liminal | K64: Suburban Uncanny
I65: Dream Logic | J65: Surreal Architecture | K65: Corporate Nightmare
H66: Research | I66: BFI / Criterion
H67: Source sheet | I67: Surreal Liminal Sources
H71: Expansion v8
H72: Focus | I72: Weird Children's | J72: Dark Family Cinema | K72: Uncanny Childhood
H73: Added | I73: 24 | J73: Existing reclassified | K73: 13
H74: Rule | I74: Cult / oddity first | J74: Dark ≠ automatically horror | K74: Family/childhood lens matters
H75: Core | I75: Return to Oz | J75: The Peanut Butter Solution | K75: The Watcher in the Woods
I76: The Secret of NIMH | J76: The Gate | K76: The Witches
I77: The Brave Little Toaster | J77: Lady in White | K77: The Mouse and His Child
H78: Adjacent | I78: Paperhouse | J78: The City of Lost Children | K78: Parents
H79: Next genre seed | I79: Kids (1995) | J79: Gen-X Youth Realism | K79: Transgressive Indie
H80: Research | I80: BFI dark kids / childhood anchors
H81: Source sheet | I81: Dark Family Sources
H86: Expansion v10
H87: Focus | I87: Forgotten Family | J87: Kids Adventure | K87: 80s/90s Video-store
H88: Added | I88: 44 | J88: Existing reclassified | K88: 5
H89: Core | I89: We're Back! | J89: The Pagemaster | K89: Richie Rich
I90: Magic Island | J90: Warriors of Virtue | K90: Camp Nowhere
I91: Gold Diggers | J91: The Borrowers | K91: 3 Ninjas
H92: Already owned | I92: We're Back! | J92: Richie Rich | K92: The Pagemaster
H93: Rule | I93: Cult/forgotten first | J93: Mainstream only reminder | K93: No blanket family catalog
H98: Expansion v11
H99: Focus | I99: Kids Creature Features | J99: Dinosaurs / Monsters | K99: Kids as leads
H100: Added | I100: 15 | J100: Existing reclassified | K100: 10
H101: Cult-first rule | I101: No generic creature catalog | J101: No obvious filler | K101: 1960–1999 only
H102: Core | I102: The Monster Squad | J102: The Gate | K102: Little Monsters
I103: Critters | J103: Invaders from Mars | K103: Making Contact
I104: Prehysteria! | J104: Dragonworld | K104: Spaced Invaders
H105: 90s oddities | I105: Pet Shop | J105: Magic in the Water | K105: Galgameth
H106: Outside range | I106: Eight Legged Freaks (2002) | J106: Not added | K106: Workbook stops at 1999
H107: Research | I107: IMDb / Paramount / Sony | J107: D23 / Full Moon | K107: See source sheet
H108: Source sheet | I108: Kids Creature Sources
H112: Expansion v12
H113: Focus | I113: Childflicks | J113: High-Concept Kids Adventure | K113: Living Toys / Miniature Worlds
H114: Added | I114: 13 | J114: Existing reclassified | K114: 9
H115: Core | I115: The Indian in the Cupboard | J115: Small Soldiers | K115: The Pagemaster
I116: Honey, I Shrunk the Kids | J116: The Borrowers | K116: The Christmas Toy
...

Sheet 1960
A1: Title | B1: Priority | C1: Genre | D1: Status | E1: Curator Tags | F1: Source
A2: Black Sunday | B2: A | C2: Gothic Horror | D2: ☐ | E2: Genre Essential | F2: Original Master v1 — curated research basis
A3: Eyes Without a Face | B3: A | C3: Horror — Subgenre Review | D3: ☐ | E3: Cult Canon | F3: Original Master v1 — curated research basis
A4: Peeping Tom | B4: A | C4: Psychological Horror | D4: ☐ | E4: Banned / Controversial | F4: Original Master v1 — curated research basis
A5: Psycho | B5: C | C5: Psychological Horror / Proto-Slasher | D5: ☐ | E5: Canon Anchor | F5: Original Master v1 — curated research basis
A6: The Brides of Dracula | B6: B | C6: Gothic Horror | D6: ☐ | E6: Genre Deep Cut | F6: Original Master v1 — curated research basis
A7: The City of the Dead | B7: B | C7: Occult Horror | D7: ☐ | E7: Genre Deep Cut | F7: Original Master v1 — curated research basis
A8: The Flesh and the Fiends | B8: B | C8: British Horror | D8: ☐ | E8: Genre Deep Cut | F8: Original Master v1 — curated research basis
A9: The Little Shop of Horrors | B9: B | C9: Horror Comedy | D9: ☐ | E9: Genre Deep Cut | F9: Original Master v1 — curated research basis
A10: The Mask of Satan | B10: A | C10: Gothic Horror | D10: ☐ | E10: Genre Essential | F10: Original Master v1 — curated research basis
A11: The Time Machine | B11: C | C11: Sci-Fi | D11: ☐ | E11: Cult Canon / Canon Anchor | F11: Original Master v1 — curated research basis
A12: Village of the Damned | B12: B | C12: Sci-Fi Horror | D12: ☐ | E12: Genre Deep Cut | F12: Original Master v1 — curated research basis
C14: In collectie | D14: =COUNTIF(D2:D12,"☑")&" / "&COUNTA(A2:A12) -> 0 / 11

Sheet 1961
A1: Title | B1: Priority | C1: Genre | D1: Status | E1: Curator Tags | F1: Source
A2: Mothra | B2: A | C2: Kaiju / Tokusatsu / Fantasy Sci-Fi | D2: ☐ | E2: Cult Canon / Genre Essential | F2: SOURCE AUDIT NEEDED — final blind-spot pass
A3: Mysterious Island | B3: B | C3: Fantasy | D3: ☐ | E3: Genre Deep Cut | F3: Original Master v1 — curated research basis
A4: The Beast of Yucca Flats | B4: A | C4: Outsider Cinema / Sci-Fi Horror / Coleman Francis | D4: ☐ | E4: So-Bad-It's-Good / Psychotronic / Regional Oddity | F4: https://en.wikipedia.org/wiki/The_Beast_of_Yucca_Flats
A5: The Curse of the Werewolf | B5: B | C5: Gothic Horror | D5: ☐ | E5: Genre Deep Cut | F5: Original Master v1 — curated research basis
A6: The Day the Earth Caught Fire | B6: A | C6: Post-Apocalyptic / Sci-Fi | D6: ☐ | E6: Genre Essential | F6: Original Master v1 — curated research basis
A7: The Innocents | B7: A | C7: Gothic Horror / Psychological Horror / Unreliable Reality | D7: ☐ | E7: Genre Essential / Visual Cult | F7: Original Master v1 — curated research basis
A8: The Pit and the Pendulum | B8: B | C8: Other / Unclassified | D8: ☐ | E8: Genre Deep Cut / Needs Genre Review | F8: Original Master v1 — curated research basis
A9: Yojimbo | B9: C | C9: Arthouse | D9: ☐ | E9: Canon Anchor | F9: Original Master v1 — curated research basis
C11: In collectie | D11: =COUNTIF(D2:D9,"☑")&" / "&COUNTA(A2:A9) -> 0 / 8

Sheet 1962
A1: Title | B1: Priority | C1: Genre | D1: Status | E1: Curator Tags | F1: Source
A2: Carnival of Souls | B2: A | C2: Psychological Horror / Supernatural Horror | D2: ☐ | E2: Cult Canon | F2: Original Master v1 — curated research basis
A3: Journey to the Seventh Planet | B3: B | C3: Sci-Fi / Fantasy | D3: ☐ | E3: Genre Deep Cut | F3: Original Master v1 — curated research basis
A4: Mondo Cane | B4: A | C4: Mondo Documentary / Shockumentary / Exploitation | D4: ☐ | E4: Genre Foundation / Controversial Cult | F4: SOURCE AUDIT NEEDED — final blind-spot pass
A5: The Awful Dr. Orlof | B5: A | C5: Horror — Subgenre Review | D5: ☐ | E5: Genre Essential | F5: Original Master v1 — curated research basis
A6: The Brain That Wouldn't Die | B6: A | C6: Horror — Subgenre Review | D6: ☐ | E6: Drive-In Classic / Psychotronic | F6: Original Master v1 — curated research basis
A7: The Day of the Triffids | B7: B | C7: Sci-Fi Horror | D7: ☐ | E7: Genre Deep Cut | F7: Original Master v1 — curated research basis
A8: The Fabulous Baron Munchausen | B8: A | C8: Fantasy / Arthouse | D8: ☐ | E8: Genre Essential | F8: Original Master v1 — curated research basis
A9: The Manchurian Candidate | B9: C | C9: Other / Unclassified | D9: ☐ | E9: Cult Canon / Canon Anchor / Needs Genre Review | F9: Original Master v1 — curated research basis
A10: The Premature Burial | B10: B | C10: Other / Unclassified | D10: ☐ | E10: Genre Deep Cut / Needs Genre Review | F10: Original Master v1 — curated research basis
C12: In collectie | D12: =COUNTIF(D2:D10,"☑")&" / "&COUNTA(A2:A10) -> 0 / 9

Sheet 1963
A1: Title | B1: Priority | C1: Genre | D1: Status | E1: Curator Tags | F1: Source
A2: Black Sabbath | B2: A | C2: Horror Anthology / Italian Horror | D2: ☐ | E2: Genre Essential | F2: Original Master v1 — curated research basis
A3: Dementia 13 | B3: A | C3: Gothic Horror | D3: ☐ | E3: Genre Essential | F3: Original Master v1 — curated research basis
A4: Matango | B4: A | C4: Japanese Sci-Fi Horror / Mutation / Island Nightmare | D4: ☐ | E4: Cult Canon / Genre Deep Cut | F4: SOURCE AUDIT NEEDED — final blind-spot pass
A5: The Birds | B5: C | C5: Nature Horror / Animal Attack | D5: ☐ | E5: Canon Anchor | F5: Original Master v1 — curated research basis
A6: The Girl Who Knew Too Much | B6: A | C6: Giallo | D6: ☐ | E6: Genre Foundation | F6: Original Master v1 — curated research basis
A7: The Haunting | B7: A | C7: Gothic Horror | D7: ☐ | E7: Genre Essential | F7: Original Master v1 — curated research basis
A8: The Kiss of the Vampire | B8: B | C8: Gothic Horror | D8: ☐ | E8: Genre Deep Cut | F8: Original Master v1 — curated research basis
A9: The Old Dark House | B9: B | C9: Comedy / Camp | D9: ☐ | E9: Camp Classic | F9: Original Master v1 — curated research basis
A10: The Raven | B10: B | C10: Comedy / Camp | D10: ☐ | E10: Camp Classic | F10: Original Master v1 — curated research basis
A11: The Sadist | B11: A | C11: Thriller / Exploitation | D11: ☐ | E11: Genre Essential | F11: Original Master v1 — curated research basis
A12: The Whip and the Body | B12: A | C12: Other / Unclassified | D12: ☐ | E12: Cult Canon / Needs Genre Review | F12: Original Master v1 — curated research basis
C14: In collectie | D14: =COUNTIF(D2:D12,"☑")&" / "&COUNTA(A2:A12) -> 0 / 11

Sheet 1964
A1: Title | B1: Priority | C1: Genre | D1: Status | E1: Curator Tags | F1: Source
A2: A Hard Day's Night | B2: A | C2: Music / Rock / Comedy | D2: ☐ | E2: Genre Essential | F2: SOURCE AUDIT NEEDED — row-level external source not retained
A3: Blood and Black Lace | B3: A | C3: Giallo / Fashion Horror / Proto-Slasher | D3: ☐ | E3: Cult Canon / Genre Foundation / Visual Cult | F3: SOURCE AUDIT NEEDED — final blind-spot pass
A4: Castle of Blood | B4: A | C4: Gothic Horror | D4: ☐ | E4: Genre Essential | F4: Original Master v1 — curated research basis
A5: Dr. Strangelove | B5: C | C5: Satire | D5: ☐ | E5: Cult Canon / Canon Anchor | F5: Original Master v1 — curated research basis
A6: Kwaidan | B6: A | C6: Arthouse | D6: ☐ | E6: Genre Essential | F6: Original Master v1 — curated research basis
A7: Onibaba | B7: A | C7: Japanese Horror | D7: ☐ | E7: Genre Essential | F7: Original Master v1 — curated research basis
A8: Santa Claus Conquers the Martians | B8: A | C8: Outsider Cinema / Kids Sci-Fi / Christmas Oddity | D8: ☐ | E8: So-Bad-It's-Good / Cult Canon / Psychotronic | F8: https://en.wikipedia.org/wiki/Santa_Claus_Conquers_the_Martians
A9: Spider Baby | B9: A | C9: Horror Comedy | D9: ☐ | E9: Cult Canon | F9: Original Master v1 — curated research basis
A10: The Creeping Terror | B10: A | C10: Outsider Cinema / Creature Sci-Fi / Regional B-Movie | D10: ☐ | E10: So-Bad-It's-Good / Regional Oddity / Cult Canon | F10: https://en.wikipedia.org/wiki/The_Creeping_Terror
A11: The Earth Dies Screaming | B11: B | C11: Sci-Fi Horror | D11: ☐ | E11: Genre Deep Cut | F11: Original Master v1 — curated research basis
A12: The Flesh Eaters | B12: A | C12: Other / Unclassified | D12: ☐ | E12: Genre Foundation / Needs Genre Review | F12: Original Master v1 — curated research basis
... A17: The Umbrellas of Cherbourg | B17: A | C17: Musical / Romance / Arthouse | D17: ☐ | E17: Genre Essential | F17: SOURCE AUDIT NEEDED — row-level external source not retained
C19: In collectie | D19: =COUNTIF(D2:D17,"☑")&" / "&COUNTA(A2:A17) -> 0 / 16

Sheet 1965
A1: Title | B1: Priority | C1: Genre | D1: Status | E1: Curator Tags | F1: Source
A2: Alphaville | B2: A | C2: Sci-Fi / Arthouse | D2: ☐ | E2: Genre Essential | F2: Original Master v1 — curated research basis
A3: Die, Monster, Die! | B3: B | C3: Cosmic Horror | D3: ☐ | E3: Genre Deep Cut | F3: Original Master v1 — curated research basis
A4: Dr. Terror's House of Horrors | B4: B | C4: Other / Unclassified | D4: ☐ | E4: Genre Deep Cut / Needs Genre Review | F4: Original Master v1 — curated research basis
A5: Faster, Pussycat! Kill! Kill! | B5: A | C5: Exploitation | D5: ☐ | E5: Genre Essential | F5: Original Master v1 — curated research basis
A6: Frankenstein Meets the Space Monster | B6: A | C6: Sci-Fi | D6: ☐ | E6: Cult Canon | F6: Original Master v1 — curated research basis
A7: Gamera, the Giant Monster | B7: A | C7: Kaiju / Tokusatsu / Japanese Monster | D7: ☐ | E7: Cult Canon / Genre Foundation | F7: SOURCE AUDIT NEEDED — final blind-spot pass
A8: Help! | B8: A | C8: Music / Rock / Comedy | D8: ☐ | E8: Genre Essential | F8: SOURCE AUDIT NEEDED — row-level external source not retained
A9: Monster a Go-Go | B9: A | C9: Outsider Cinema / Sci-Fi Horror / Regional Oddity | D9: ☐ | E9: So-Bad-It's-Good / Cult Oddity | F9: https://en.wikipedia.org/wiki/Monster_a_Go-Go
A10: Orgy of the Dead | B10: A | C10: Other / Unclassified | D10: ☐ | E10: Psychotronic / Needs Genre Review | F10: Original Master v1 — curated research basis
A11: Planet of the Vampires | B11: A | C11: Sci-Fi Horror | D11: ☐ | E11: Genre Essential | F11: Original Master v1 — curated research basis
A12: Repulsion | B12: A | C12: Psychological Horror / Subjective Horror / Apartment Horror | D12: ☐ | E12: Cult Canon / Genre Essential / Visual Cult | F12: https://whatson.bfi.org.uk/Online/default.asp?BOparam%3A%3AWScontent%3A%3AloadArticle%3A%3Apermalink=repulsion
... A14: The Skull | B14: B | C14: Horror — Subgenre Review | D14: ☐ | E14: Genre Deep Cut | F14: Original Master v1 — curated research basis
C16: In collectie | D16: =COUNTIF(D2:D14,"☑")&" / "&COUNTA(A2:A14) -> 0 / 13

Sheet 1966
A1: Title | B1: Priority | C1: Genre | D1: Status | E1: Curator Tags | F1: Source
A2: Come Drink with Me | B2: A | C2: Classic Hong Kong Kung Fu / Wuxia / Shaw Brothers / Foundation | D2: ☐ | E2: Genre Foundation | F2: https://www.bfi.org.uk/features/where-begin-with-shaw-brothers
A3: Django | B3: A | C3: Western | D3: ☐ | E3: Cult Canon | F3: Original Master v1 — curated research basis
A4: Dracula: Prince of Darkness | B4: B | C4: Gothic Horror | D4: ☐ | E4: Genre Deep Cut | F4: Original Master v1 — curated research basis
A5: Fantastic Voyage | B5: C | C5: Science Adventure / Miniaturization / Medical Sci-Fi | D5: ☐ | E5: Canon Anchor / Genre Foundation | F5: https://en.wikipedia.org/wiki/Fantastic_Voyage
A6: Gamera vs. Barugon | B6: A | C6: Kaiju / Tokusatsu / Monster Battle | D6: ☐ | E6: Franchise Essential / Genre Deep Cut | F6: SOURCE AUDIT NEEDED — final blind-spot pass
A7: Kill, Baby... Kill! | B7: A | C7: Gothic Horror | D7: ☐ | E7: Genre Essential | F7: Original Master v1 — curated research basis
A8: Manos: The Hands of Fate | B8: A | C8: Outsider Cinema / Folk Horror / Amateur Regional | D8: ☐ | E8: So-Bad-It's-Good / Cult Canon / Regional Oddity | F8: https://www.amateurcinema.org/index.php/film/manos-the-hands-of-fate
A9: Persona | B9: C | C9: Psychological Surrealism / Identity Horror / Arthouse | D9: ☐ | E9: Canon Anchor / Genre Foundation / Identity Cinema | F9: https://www.bfi.org.uk/lists/persona-films-inspired-ingmar-bergman-60th-anniversary
A10: Rat Pfink a Boo Boo | B10: A | C10: Outsider Cinema / Superhero Parody / Ray Dennis Steckler | D10: ☐ | E10: Psychotronic / Cult Oddity / Regional Oddity | F10: https://en.wikipedia.org/wiki/Rat_Pfink_a_Boo_Boo
A11: Seconds | B11: A | C11: Paranoid Sci-Fi / Identity Horror / Psychological Thriller | D11: ☐ | E11: Cult Canon / Genre Essential | F11: Original Master v1 — curated research basis
A12: The Big Gundown | B12: A | C12: Spaghetti Western / Political Western / Manhunt | D12: ☐ | E12: Genre Essential / Cult Classic | F12: SOURCE AUDIT NEEDED — final blind-spot pass
... A19: The Wild Angels | B19: A | C19: Biker / Action / Exploitation | D19: ☐ | E19: Genre Essential | F19: Original Master v1 — curated research basis
C21: In collectie | D21: =COUNTIF(D2:D19,"☑")&" / "&COUNTA(A2:A19) -> 0 / 18

Sheet 1967
A1: Title | B1: Priority | C1: Genre | D1: Status | E1: Curator Tags | F1: Source
A2: Argoman the Fantastic Superman | B2: B | C2: Other / Unclassified | D2: ☐ | E2: Genre Deep Cut / Needs Genre Review | F2: Original Master v1 — curated research basis
A3: Branded to Kill | B3: A | C3: Other / Unclassified | D3: ☐ | E3: Cult Canon / Needs Genre Review | F3: Original Master v1 — curated research basis
A4: David Holzman's Diary | B4: A | C4: Mockumentary Foundation / Meta-Cinema / American Indie | D4: ☐ | E4: Genre Foundation | F4: https://en.wikipedia.org/wiki/David_Holzman%27s_Diary
A5: One-Armed Swordsman | B5: A | C5: Classic Hong Kong Kung Fu / Wuxia / Shaw Brothers | D5: ☐ | E5: Cult Canon | F5: https://www.bfi.org.uk/lists/10-great-wuxia-swordplay-films
A6: Point Blank | B6: A | C6: Crime / Noir | D6: ☐ | E6: Cult Canon | F6: Original Master v1 — curated research basis
A7: Privilege | B7: A | C7: Sci-Fi / Dystopian | D7: ☐ | E7: Cult Canon | F7: Original Master v1 — curated research basis
A8: Quatermass and the Pit | B8: A | C8: Sci-Fi Horror | D8: ☐ | E8: Genre Essential | F8: Original Master v1 — curated research basis
A9: Samurai Rebellion | B9: B | C9: Arthouse | D9: ☐ | E9: Genre Deep Cut | F9: Original Master v1 — curated research basis
A10: She Freak | B10: A | C10: Exploitation | D10: ☐ | E10: Genre Essential | F10: Original Master v1 — curated research basis
A11: The Fearless Vampire Killers | B11: B | C11: Horror Comedy | D11: ☐ | E11: Genre Deep Cut | F11: Original Master v1 — curated research basis
A12: The Gruesome Twosome | B12: A | C12: Other / Unclassified | D12: ☐ | E12: Cult Canon / Needs Genre Review | F12: Original Master v1 — curated research basis
... A17: This Night I'll Possess Your Corpse | B17: A | C17: Horror — Subgenre Review | D17: ☐ | E17: Genre Essential | F17: Original Master v1 — curated research basis
C19: In collectie | D19: =COUNTIF(D2:D17,"☑")&" / "&COUNTA(A2:A17) -> 0 / 16

Sheet 1968
A1: Title | B1: Priority | C1: Genre | D1: Status | E1: Curator Tags | F1: Source
A2: Barbarella | B2: A | C2: Sci-Fi / Comedy / Camp | D2: ☐ | E2: Camp Classic | F2: Original Master v1 — curated research basis
A3: Danger: Diabolik | B3: A | C3: Other / Unclassified | D3: ☐ | E3: Cult Canon / Needs Genre Review | F3: Original Master v1 — curated research basis
A4: Destroy All Monsters | B4: A | C4: Kaiju / Tokusatsu / Monster Ensemble | D4: ☐ | E4: Cult Canon / Franchise Essential | F4: SOURCE AUDIT NEEDED — final blind-spot pass
A5: Goke, Body Snatcher from Hell | B5: A | C5: Sci-Fi Horror | D5: ☐ | E5: Genre Essential | F5: Original Master v1 — curated research basis
A6: Head | B6: A | C6: Music / Psychedelic | D6: ☐ | E6: Visual Cult | F6: SOURCE AUDIT NEEDED — row-level external source not retained
A7: Hour of the Wolf | B7: A | C7: Psychological Horror / Folk Horror / Hallucinatory Reality | D7: ☐ | E7: Cult Canon / Genre Essential / Visual Cult | F7: https://www.bfi.org.uk/features/ingmar-bergman-folk-horror-pioneer
A8: Night of the Living Dead | B8: A | C8: Zombie Horror / Siege Horror | D8: ☐ | E8: Genre Essential | F8: Original Master v1 — curated research basis
A9: Planet of the Apes | B9: C | C9: Dystopian Sci-Fi / Social Sci-Fi / Post-Apocalyptic | D9: ☐ | E9: Canon Anchor / Genre Essential | F9: https://en.wikipedia.org/wiki/Planet_of_the_Apes_(1968_film)
A10: Rosemary's Baby | B10: C | C10: Psychological Horror / Occult Horror / Apartment Paranoia | D10: ☐ | E10: Canon Anchor / Genre Essential | F10: Original Master v1 — curated research basis
A11: Spirits of the Dead | B11: B | C11: Horror Anthology | D11: ☐ | E11: Genre Deep Cut | F11: Original Master v1 — curated research basis
A12: Symbiopsychotaxiplasm: Take One | B12: A | C12: Experimental | D12: ☐ | E12: Cult Canon | F12: Original Master v1 — curated research basis
... A24: Yellow Submarine | B24: A | C24: Animation / Music / Psychedelic | D24: ☐ | E24: Visual Cult | F24: SOURCE AUDIT NEEDED — row-level external source not retained
C26: In collectie | D26: =COUNTIF(D2:D24,"☑")&" / "&COUNTA(A2:A24) -> 0 / 23

Sheet 1969
A1: Title | B1: Priority | C1: Genre | D1: Status | E1: Curator Tags | F1: Source
A2: All Monsters Attack | B2: B | C2: Kaiju / Kids Fantasy / Franchise Oddity | D2: ☐ | E2: Franchise Deep Cut / Cult Oddity | F2: SOURCE AUDIT NEEDED — final blind-spot pass
A3: All the Colors of the Dark | B3: A | C3: Giallo | D3: ☐ | E3: Visual Cult | F3: Original Master v1 — curated research basis
A4: Blind Beast | B4: A | C4: Arthouse | D4: ☐ | E4: Genre Essential | F4: Original Master v1 — curated research basis
A5: Fando y Lis | B5: A | C5: Arthouse / Surreal | D5: ☐ | E5: Cult Canon | F5: Original Master v1 — curated research basis
A6: Funeral Parade of Roses | B6: A | C6: Arthouse | D6: ☐ | E6: Cult Canon | F6: Original Master v1 — curated research basis
A7: Horrors of Malformed Men | B7: A | C7: Other / Unclassified | D7: ☐ | E7: Cult Canon / Needs Genre Review | F7: Original Master v1 — curated research basis
A8: Stereo | B8: A | C8: Sci-Fi / Experimental | D8: ☐ | E8: Genre Essential | F8: Original Master v1 — curated research basis
A9: The Bed Sitting Room | B9: A | C9: Post-Apocalyptic / Arthouse / Absurdist | D9: ☐ | E9: Genre Essential | F9: https://www.mondo-digital.com/bronxwarriors.html
A10: The Cremator | B10: A | C10: Psychological Horror / Black Comedy / Surrealism | D10: ☐ | E10: Cult Canon / Visual Cult / Genre Deep Cut | F10: Original Master v1 — curated research basis
A11: The Haunted House of Horror | B11: B | C11: Horror — Subgenre Review | D11: ☐ | E11: Genre Deep Cut | F11: Original Master v1 — curated research basis
A12: The Illustrated Man | B12: B | C12: Sci-Fi | D12: ☐ | E12: Cult Oddity | F12: Original Master v1 — curated research basis
... A15: Venus in Furs | B15: A | C15: Erotic | D15: ☐ | E15: Visual Cult | F15: Original Master v1 — curated research basis
C17: In collectie | D17: =COUNTIF(D2:D15,"☑")&" / "&COUNTA(A2:A15) -> 0 / 14

Sheet 1970
A1: Title | B1: Priority | C1: Genre | D1: Status | E1: Curator Tags | F1: Source
A2: A Walk In The Spring Rain | B2: B | C2: Other / Unclassified | D2: ☐ | E2: Genre Deep Cut / Needs Genre Review | F2: Original Master v1 — curated research basis
A3: Adam At Six A.M | B3: B | C3: Other / Unclassified | D3: ☐ | E3: Genre Deep Cut / Needs Genre Review | F3: Original Master v1 — curated research basis
A4: Airport | B4: B | C4: Other / Unclassified | D4: ☐ | E4: Genre Deep Cut / Needs Genre Review | F4: Original Master v1 — curated research basis
A5: And Soon The Darkness | B5: B | C5: Other / Unclassified | D5: ☐ | E5: Genre Deep Cut / Needs Genre Review | F5: Original Master v1 — curated research basis
A6: Angel Unchained | B6: B | C6: Other / Unclassified | D6: ☐ | E6: Genre Deep Cut / Needs Genre Review | F6: Original Master v1 — curated research basis
A7: Beast of Blood | B7: B | C7: Exploitation Horror | D7: ☐ | E7: Genre Deep Cut | F7: Original Master v1 — curated research basis
A8: Beneath the Planet of the Apes | B8: B | C8: Dystopian Sci-Fi / Post-Apocalyptic / Mutant Cult | D8: ☐ | E8: Franchise Essential / Genre Deep Cut | F8: https://en.wikipedia.org/wiki/Beneath_the_Planet_of_the_Apes
A9: Beyond the Valley of the Dolls | B9: A | C9: Comedy / Camp | D9: ☐ | E9: Camp Classic | F9: Original Master v1 — curated research basis
A10: Bigfoot The Movie | B10: B | C10: Other / Unclassified | D10: ☐ | E10: Genre Deep Cut / Needs Genre Review | F10: Original Master v1 — curated research basis
A11: Bombay Talkie | B11: B | C11: Other / Unclassified | D11: ☐ | E11: Genre Deep Cut / Needs Genre Review | F11: Original Master v1 — curated research basis
A12: Carry On Up the Jungle | B12: B | C12: Other / Unclassified | D12: ☐ | E12: Genre Deep Cut / Needs Genre Review | F12: Original Master v1 — curated research basis
... A65: Wuthering Heights | B65: B | C65: Other / Unclassified | D65: ☐ | E65: Genre Deep Cut / Needs Genre Review | F65: Original Master v1 — curated research basis
C67: In collectie | D67: =COUNTIF(D2:D65,"☑")&" / "&COUNTA(A2:A65) -> 0 / 64

Sheet 1971
A1: Title | B1: Priority | C1: Genre | D1: Status | E1: Curator Tags | F1: Source
A2: $ | B2: B | C2: Other / Unclassified | D2: ☐ | E2: Genre Deep Cut / Needs Genre Review | F2: Original Master v1 — curated research basis
A3: 200 Motels | B3: B | C3: Other / Unclassified | D3: ☐ | E3: Genre Deep Cut / Needs Genre Review | F3: Original Master v1 — curated research basis
A4: A Clockwork Orange | B4: C | C4: Sci-Fi / Dystopian | D4: ☐ | E4: Cult Canon / Canon Anchor | F4: Original Master v1 — curated research basis
A5: A Lizard in a Woman's Skin | B5: A | C5: Giallo / Psychological Thriller / Psychedelic | D5: ☐ | E5: Genre Essential / Visual Cult | F5: SOURCE AUDIT NEEDED — final blind-spot pass
A6: A Lizard in a Woman's Skin/Schizoid | B6: B | C6: Other / Unclassified | D6: ☐ | E6: Genre Deep Cut / Needs Genre Review | F6: Original Master v1 — curated research basis
A7: A Touch of Zen | B7: A | C7: Classic Hong Kong Martial Arts / Wuxia / King Hu / Arthouse Cult | D7: ☐ | E7: Cult Canon | F7: https://www.bfi.org.uk/lists/great-action-film-every-year-1924-now
A8: A Town Called Hell | B8: B | C8: Exploitation Horror | D8: ☐ | E8: Genre Deep Cut | F8: Original Master v1 — curated research basis
A9: Beast of the Yellow Night | B9: B | C9: Other / Unclassified | D9: ☐ | E9: Genre Deep Cut / Needs Genre Review | F9: Original Master v1 — curated research basis
A10: Black Beauty | B10: B | C10: Other / Unclassified | D10: ☐ | E10: Genre Deep Cut / Needs Genre Review | F10: Original Master v1 — curated research basis
A11: Bunny O'Hare | B11: B | C11: Other / Unclassified | D11: ☐ | E11: Genre Deep Cut / Needs Genre Review | F11: Original Master v1 — curated research basis
A12: Carnal Knowledge | B12: B | C12: Other / Unclassified | D12: ☐ | E12: Genre Deep Cut / Needs Genre Review | F12: Original Master v1 — curated research basis
... A75: Women In Cages | B75: B | C75: Other / Unclassified | D75: ☐ | E75: Genre Deep Cut / Needs Genre Review | F75: Original Master v1 — curated research basis
C77: In collectie | D77: =COUNTIF(D2:D75,"☑")&" / "&COUNTA(A2:A75) -> 0 / 74

Sheet 1972
A1: Title | B1: Priority | C1: Genre | D1: Status | E1: Curator Tags | F1: Source
A2: 43: The Richard Petty Story | B2: B | C2: Other / Unclassified | D2: ☐ | E2: Genre Deep Cut / Needs Genre Review | F2: Original Master v1 — curated research basis
A3: A Reason to Live, a Reason to Die | B3: B | C3: Other / Unclassified | D3: ☐ | E3: Genre Deep Cut / Needs Genre Review | F3: Original Master v1 — curated research basis
A4: Across 110th Street | B4: B | C4: Other / Unclassified | D4: ☐ | E4: Genre Deep Cut / Needs Genre Review | F4: Original Master v1 — curated research basis
A5: Asylum | B5: B | C5: Other / Unclassified | D5: ☐ | E5: Genre Deep Cut / Needs Genre Review | F5: Original Master v1 — curated research basis
A6: Beware! The Blob | B6: B | C6: Other / Unclassified | D6: ☐ | E6: Genre Deep Cut / Needs Genre Review | F6: Original Master v1 — curated research basis
A7: Blacula | B7: A | C7: Horror — Subgenre Review | D7: ☐ | E7: Genre Essential | F7: Original Master v1 — curated research basis
A8: Blood Freak | B8: B | C8: Exploitation Horror | D8: ☐ | E8: Genre Deep Cut | F8: Original Master v1 — curated research basis
A9: Buck and the Preacher | B9: A | C9: Black Western / Adventure | D9: ☐ | E9: Genre Essential | F9: SOURCE AUDIT NEEDED — row-level external source not retained
A10: Bury Me an Angel | B10: B | C10: Other / Unclassified | D10: ☐ | E10: Genre Deep Cut / Needs Genre Review | F10: Original Master v1 — curated research basis
A11: Butterflies Are Free | B11: B | C11: Other / Unclassified | D11: ☐ | E11: Genre Deep Cut / Needs Genre Review | F11: Original Master v1 — curated research basis
A12: Cabaret | B12: A | C12: Musical / Drama / Arthouse | D12: ☐ | E12: Genre Essential | F12: SOURCE AUDIT NEEDED — row-level external source not retained
... A73: You'll Like My Mother | B73: B | C73: Other / Unclassified | D73: ☐ | E73: Genre Deep Cut / Needs Genre Review | F73: Original Master v1 — curated research basis
C75: In collectie | D75: =COUNTIF(D2:D73,"☑")&" / "&COUNTA(A2:A73) -> 0 / 72

Sheet 1973
A1: Title | B1: Priority | C1: Genre | D1: Status | E1: Curator Tags | F1: Source
A2: A Name For Evil | B2: B | C2: Exploitation Horror | D2: ☐ | E2: Genre Deep Cut | F2: Original Master v1 — curated research basis
A3: A Warm December | B3: B | C3: Other / Unclassified | D3: ☐ | E3: Genre Deep Cut / Needs Genre Review | F3: Original Master v1 — curated research basis
A4: Ace Eli and Rodger of the Skies | B4: B | C4: Other / Unclassified | D4: ☐ | E4: Genre Deep Cut / Needs Genre Review | F4: Original Master v1 — curated research basis
A5: Alvin Purple | B5: B | C5: Ozploitation / Ocker Comedy / Sex Comedy | D5: ☐ | E5: Genre Deep Cut | F5: https://www.bfi.org.uk/features/fast-track-fandom-beginners-guide-through-ozploitation-movies
A6: And Now the Screaming Starts! | B6: B | C6: Sci-Fi / Fantasy | D6: ☐ | E6: Genre Deep Cut | F6: Original Master v1 — curated research basis
A7: Arnold | B7: B | C7: Other / Unclassified | D7: ☐ | E7: Genre Deep Cut / Needs Genre Review | F7: Original Master v1 — curated research basis
A8: Badlands | B8: B | C8: Other / Unclassified | D8: ☐ | E8: Genre Deep Cut / Needs Genre Review | F8: Original Master v1 — curated research basis
A9: Baffled! | B9: B | C9: Other / Unclassified | D9: ☐ | E9: Genre Deep Cut / Needs Genre Review | F9: Original Master v1 — curated research basis
A10: Battle for the Planet of the Apes | B10: B | C10: Post-Apocalyptic Sci-Fi / Franchise / Social Sci-Fi | D10: ☐ | E10: Franchise Deep Cut / Completion | F10: https://en.wikipedia.org/wiki/Battle_for_the_Planet_of_the_Apes
A11: Belladonna of Sadness | B11: A | C11: Adult Animation / Psychedelic / Arthouse | D11: ☐ | E11: Visual Cult | F11: https://www.bfi.org.uk/sight-and-sound/lists/50-key-anime-films
A12: Beyond Atlantis | B12: B | C12: Other / Unclassified | D12: ☐ | E12: Genre Deep Cut / Needs Genre Review | F12: Original Master v1 — curated research basis
... A78: Your Three Minutes Are Up | B78: B | C78: Other / Unclassified | D78: ☐ | E78: Genre Deep Cut / Needs Genre Review | F78: Original Master v1 — curated research basis
C80: In collectie | D80: =COUNTIF(D2:D78,"☑")&" / "&COUNTA(A2:A78) -> 0 / 77

Sheet 1974
A1: Title | B1: Priority | C1: Genre | D1: Status | E1: Curator Tags | F1: Source
A2: A Quiet Day in Belfast | B2: B | C2: Other / Unclassified | D2: ☐ | E2: Genre Deep Cut / Needs Genre Review | F2: Original Master v1 — curated research basis
A3: Abby | B3: B | C3: Other / Unclassified | D3: ☐ | E3: Genre Deep Cut / Needs Genre Review | F3: Original Master v1 — curated research basis
A4: Act Of Vengeance | B4: B | C4: Other / Unclassified | D4: ☐ | E4: Genre Deep Cut / Needs Genre Review | F4: Original Master v1 — curated research basis
A5: Almost Human | B5: A | C5: Poliziotteschi / Eurocrime / Serial Criminal / Nihilistic Cult | D5: ☐ | E5: Genre Essential | F5: https://en.wikipedia.org/wiki/Poliziotteschi
A6: Bad Ronald | B6: A | C6: Made-for-TV Thriller / Psychological Horror / Hidden-Room Horror | D6: ☐ | E6: TV Cult / Cult Classic | F6: SOURCE AUDIT NEEDED — final blind-spot pass
A7: Benji | B7: B | C7: Other / Unclassified | D7: ☐ | E7: Genre Deep Cut / Needs Genre Review | F7: Original Master v1 — curated research basis
A8: Big Bad Mama | B8: B | C8: Other / Unclassified | D8: ☐ | E8: Genre Deep Cut / Needs Genre Review | F8: Original Master v1 — curated research basis
A9: Black Belt Jones | B9: B | C9: Blaxploitation / Martial Arts / Action | D9: ☐ | E9: Genre Deep Cut | F9: Original Master v1 — curated research basis
A10: Black Christmas | B10: A | C10: Proto-Slasher | D10: ☐ | E10: Genre Foundation | F10: Original Master v1 — curated research basis
A11: Black Streetfighter/Black Fist | B11: B | C11: Other / Unclassified | D11: ☐ | E11: Genre Deep Cut / Needs Genre Review | F11: Original Master v1 — curated research basis
A12: Blueblood | B12: B | C12: Exploitation Horror | D12: ☐ | E12: Genre Deep Cut | F12: Original Master v1 — curated research basis
... A67: Zardoz | B67: A | C67: Sci-Fi | D67: ☐ | E67: Cult Oddity | F67: Original Master v1 — curated research basis
C69: In collectie | D69: =COUNTIF(D2:D67,"☑")&" / "&COUNTA(A2:A67) -> 0 / 66

Sheet 1975
A1: Title | B1: Priority | C1: Genre | D1: Status | E1: Curator Tags | F1: Source
A2: 92 in the Shade | B2: B | C2: Other / Unclassified | D2: ☐ | E2: Genre Deep Cut / Needs Genre Review | F2: Original Master v1 — curated research basis
A3: A Boy and His Dog | B3: A | C3: Post-Apocalyptic / Dark Comedy | D3: ☐ | E3: Cult Canon | F3: https://www.mondo-digital.com/bronxwarriors.html
A4: Bad, Black and Beautiful | B4: B | C4: Other / Unclassified | D4: ☐ | E4: Genre Deep Cut / Needs Genre Review | F4: Original Master v1 — curated research basis
A5: Barry Lyndon | B5: B | C5: Other / Unclassified | D5: ☐ | E5: Genre Deep Cut / Needs Genre Review | F5: Original Master v1 — curated research basis
A6: Cooley High | B6: A | C6: Black Cinema / Coming-of-age / Comedy-Drama | D6: ☐ | E6: Genre Essential | F6: SOURCE AUDIT NEEDED — row-level external source not retained
A7: Coonskin | B7: A | C7: Adult Animation / Satire / Blaxploitation Deconstruction | D7: ☐ | E7: Cult Canon | F7: https://www.bfi.org.uk/lists/10-great-blaxploitation-movies
A8: Deafula | B8: B | C8: Other / Unclassified | D8: ☐ | E8: Genre Deep Cut / Needs Genre Review | F8: Original Master v1 — curated research basis
A9: Death Race 2000 | B9: A | C9: Exploitation Horror | D9: ☐ | E9: Genre Essential | F9: Original Master v1 — curated research basis
A10: Deep Red | B10: A | C10: Giallo | D10: ☐ | E10: Genre Essential | F10: Original Master v1 — curated research basis
A11: Dersu Uzala | B11: B | C11: Other / Unclassified | D11: ☐ | E11: Genre Deep Cut / Needs Genre Review | F11: Original Master v1 — curated research basis
A12: Dolemite | B12: A | C12: Blaxploitation / Comedy / Martial Arts | D12: ☐ | E12: Cult Canon | F12: SOURCE AUDIT NEEDED — row-level external source not retained
... A54: Zorro | B54: B | C54: Other / Unclassified | D54: ☐ | E54: Genre Deep Cut / Needs Genre Review | F54: Original Master v1 — curated research basis
C56: In collectie | D56: =COUNTIF(D2:D54,"☑")&" / "&COUNTA(A2:A54) -> 0 / 53

Sheet 1976
A1: Title | B1: Priority | C1: Genre | D1: Status | E1: Curator Tags | F1: Source
A2: Aces High | B2: B | C2: Other / Unclassified | D2: ☐ | E2: Genre Deep Cut / Needs Genre Review | F2: Original Master v1 — curated research basis
A3: Alice, Sweet Alice | B3: A | C3: Slasher / Religious Horror | D3: ☐ | E3: Cult Canon | F3: Original Master v1 — curated research basis
A4: Apple Pie | B4: B | C4: Other / Unclassified | D4: ☐ | E4: Genre Deep Cut / Needs Genre Review | F4: Original Master v1 — curated research basis
A5: Assault on Precinct 13 | B5: A | C5: Action | D5: ☐ | E5: Cult Canon | F5: Original Master v1 — curated research basis
A6: Bittersweet Love | B6: B | C6: Other / Unclassified | D6: ☐ | E6: Genre Deep Cut / Needs Genre Review | F6: Original Master v1 — curated research basis
A7: Black Samurai | B7: B | C7: Blaxploitation / Martial Arts / Action | D7: ☐ | E7: Genre Deep Cut | F7: SOURCE AUDIT NEEDED — row-level external source not retained
A8: Bloodsucking Freaks | B8: B | C8: Exploitation Horror | D8: ☐ | E8: Genre Deep Cut | F8: Original Master v1 — curated research basis
A9: Bruce Lee Fights Back from the Grave | B9: A | C9: Bruceploitation / Exploitation Marketing / Kung Fu Cult | D9: ☐ | E9: Cult Canon | F9: https://en.wikipedia.org/wiki/Bruce_Lee_Fights_Back_from_the_Grave
A10: Bugsy Malone | B10: B | C10: Other / Unclassified | D10: ☐ | E10: Genre Deep Cut / Needs Genre Review | F10: Original Master v1 — curated research basis
A11: Burnt Offerings | B11: B | C11: Psychological Horror / Haunted House / Possession | D11: ☐ | E11: Genre Deep Cut / Slow-Burn Cult | F11: Original Master v1 — curated research basis
A12: Car Wash | B12: A | C12: Black Ensemble Comedy / Music | D12: ☐ | E12: Genre Essential | F12: SOURCE AUDIT NEEDED — row-level external source not retained
... A64: Track of the Moon Beast | B64: B | C64: Other / Unclassified | D64: ☐ | E64: Genre Deep Cut / Needs Genre Review | F64: Original Master v1 — curated research basis
C66: In collectie | D66: =COUNTIF(D2:D64,"☑")&" / "&COUNTA(A2:A64) -> 0 / 63

Sheet 1977
A1: Title | B1: Priority | C1: Genre | D1: Status | E1: Curator Tags | F1: Source
A2: 3 Women | B2: B | C2: Psychological Surrealism / Identity Horror / Dream Logic | D2: ☐ | E2: Genre Deep Cut / Visual Cult / Identity Cinema | F2: Original Master v1 — curated research basis
A3: A Little Night Music | B3: B | C3: Other / Unclassified | D3: ☐ | E3: Genre Deep Cut / Needs Genre Review | F3: Original Master v1 — curated research basis
A4: ABBA: The Movie | B4: B | C4: Other / Unclassified | D4: ☐ | E4: Genre Deep Cut / Needs Genre Review | F4: Original Master v1 — curated research basis
A5: Blue Sunshine | B5: A | C5: Other / Unclassified | D5: ☐ | E5: Cult Canon / Needs Genre Review | F5: Original Master v1 — curated research basis
A6: Bobby Deerfield | B6: B | C6: Other / Unclassified | D6: ☐ | E6: Genre Deep Cut / Needs Genre Review | F6: Original Master v1 — curated research basis
A7: Checkered Flag or Crash | B7: B | C7: Other / Unclassified | D7: ☐ | E7: Genre Deep Cut / Needs Genre Review | F7: Original Master v1 — curated research basis
A8: Close Encounters of the Third Kind | B8: B | C8: Other / Unclassified | D8: ☐ | E8: Genre Deep Cut / Needs Genre Review | F8: Original Master v1 — curated research basis
A9: Damnation Alley | B9: B | C9: Post-Apocalyptic / Road Movie / Sci-Fi | D9: ☐ | E9: Genre Deep Cut | F9: https://www.mondo-digital.com/bronxwarriors.html
A10: Death Bed: The Bed That Eats | B10: A | C10: Outsider Horror / Surreal Regional / Killer Object | D10: ☐ | E10: Cult Oddity / Regional Oddity / Psychotronic | F10: https://en.wikipedia.org/wiki/Death_Bed:_The_Bed_That_Eats
A11: Death Promise | B11: B | C11: Exploitation Horror | D11: ☐ | E11: Genre Deep Cut | F11: Original Master v1 — curated research basis
A12: Demon Seed | B12: A | C12: Exploitation Horror | D12: ☐ | E12: Genre Essential | F12: Original Master v1 — curated research basis
... A56: You Light Up My Life | B56: B | C56: Other / Unclassified | D56: ☐ | E56: Genre Deep Cut / Needs Genre Review | F56: Original Master v1 — curated research basis
C58: In collectie | D58: =COUNTIF(D2:D56,"☑")&" / "&COUNTA(A2:A56) -> 0 / 55

Sheet 1978
A1: Title | B1: Priority | C1: Genre | D1: Status | E1: Curator Tags | F1: Source
A2: A Dream Of Passion | B2: B | C2: Other / Unclassified | D2: ☐ | E2: Genre Deep Cut / Needs Genre Review | F2: Original Master v1 — curated research basis
A3: Animal House | B3: A | C3: College Comedy / Raunch | D3: ☐ | E3: Cult Canon | F3: SOURCE AUDIT NEEDED — row-level external source not retained
A4: Avalanche | B4: B | C4: Other / Unclassified | D4: ☐ | E4: Genre Deep Cut / Needs Genre Review | F4: Original Master v1 — curated research basis
A5: Big Wednesday | B5: B | C5: Other / Unclassified | D5: ☐ | E5: Genre Deep Cut / Needs Genre Review | F5: Original Master v1 — curated research basis
A6: Blue Collar | B6: A | C6: Black Cinema / Crime / Working-Class Drama | D6: ☐ | E6: Genre Essential | F6: Original Master v1 — curated research basis
A7: Crippled Avengers | B7: A | C7: Classic Kung Fu / Shaw Brothers / Venom Mob | D7: ☐ | E7: Cult Canon | F7: https://www.bfi.org.uk/features/where-begin-with-shaw-brothers
A8: Cycle Vixens | B8: B | C8: Other / Unclassified | D8: ☐ | E8: Genre Deep Cut / Needs Genre Review | F8: Original Master v1 — curated research basis
A9: Dawn of the Dead | B9: A | C9: Zombie Horror | D9: ☐ | E9: Cult Canon | F9: Original Master v1 — curated research basis
A10: Deathsport | B10: B | C10: Exploitation Horror | D10: ☐ | E10: Genre Deep Cut | F10: Original Master v1 — curated research basis
A11: Disco Fever | B11: B | C11: Disco / Drama | D11: ☐ | E11: Genre Deep Cut | F11: Original Master v1 — curated research basis
A12: Drunken Master | B12: A | C12: Classic Kung Fu / Jackie Chan / Comedy | D12: ☐ | E12: Cult Canon / Genre Essential | F12: https://www.bfi.org.uk/lists/10-great-kung-fu-films
... A69: Who Is Killing the Great Chefs of Europe? | B69: B | C69: Other / Unclassified | D69: ☐ | E69: Genre Deep Cut / Needs Genre Review | F69: Original Master v1 — curated research basis
C71: In collectie | D71: =COUNTIF(D2:D69,"☑")&" / "&COUNTA(A2:A69) -> 0 / 68

Sheet 1979
A1: Title | B1: Priority | C1: Genre | D1: Status | E1: Curator Tags | F1: Source
A2: Alien | B2: C | C2: Sci-Fi Horror | D2: ☐ | E2: Canon Anchor | F2: Original Master v1 — curated research basis
A3: All That Jazz | B3: A | C3: Musical / Dance / Arthouse | D3: ☐ | E3: Genre Essential | F3: SOURCE AUDIT NEEDED — row-level external source not retained
A4: Americathon | B4: B | C4: Other / Unclassified | D4: ☐ | E4: Genre Deep Cut / Needs Genre Review | F4: Original Master v1 — curated research basis
A5: Caligula | B5: A | C5: Erotic Historical / Exploitation / Notorious Production | D5: ☐ | E5: Notorious Cult / Alternate Cut History / Banned / Controversial | F5: SOURCE AUDIT NEEDED — final blind-spot pass
A6: Chapter Two | B6: B | C6: Other / Unclassified | D6: ☐ | E6: Genre Deep Cut / Needs Genre Review | F6: Original Master v1 — curated research basis
A7: Chilly Scenes Of Winter | B7: B | C7: Other / Unclassified | D7: ☐ | E7: Genre Deep Cut / Needs Genre Review | F7: Original Master v1 — curated research basis
A8: Cuba | B8: B | C8: Other / Unclassified | D8: ☐ | E8: Genre Deep Cut / Needs Genre Review | F8: Original Master v1 — curated research basis
A9: Dirty Ho | B9: A | C9: Classic Kung Fu / Shaw Brothers / Lau Kar-leung | D9: ☐ | E9: Cult Canon | F9: https://www.bfi.org.uk/features/where-begin-with-shaw-brothers
A10: Disco Godfather | B10: B | C10: Disco / Blaxploitation | D10: ☐ | E10: Genre Deep Cut | F10: Original Master v1 — curated research basis
A11: Hair | B11: A | C11: Rock Musical / Counterculture | D11: ☐ | E11: Soundtrack Cult | F11: SOURCE AUDIT NEEDED — row-level external source not retained
A12: Human Experiments | B12: B | C12: Other / Unclassified | D12: ☐ | E12: Genre Deep Cut / Needs Genre Review | F12: Original Master v1 — curated research basis
... A55: Weasels Rip My Flesh | B55: B | C55: Other / Unclassified | D55: ☐ | E55: Genre Deep Cut / Needs Genre Review | F55: Original Master v1 — curated research basis
C57: In collectie | D57: =COUNTIF(D2:D55,"☑")&" / "&COUNTA(A2:A55) -> 0 / 54

Sheet 1980
A1: Title | B1: Priority | C1: Genre | D1: Status | E1: Curator Tags | F1: Source
A2: Airplane! | B2: A | C2: Spoof / Parody / Slapstick | D2: ☐ | E2: Genre Essential | F2: SOURCE AUDIT NEEDED — row-level external source not retained
A3: Alligator | B3: A | C3: Creature Feature | D3: ☐ | E3: Creature Feature | F3: Original Master v1 — curated research basis
A4: Altered States | B4: A | C4: Body Horror | D4: ☐ | E4: Visual Cult | F4: https://www.criterion.com/films/29506-altered-states
A5: Atlantic City | B5: B | C5: Other / Unclassified | D5: ☐ | E5: Genre Deep Cut / Needs Genre Review | F5: Original Master v1 — curated research basis
A6: Battle Beyond the Stars | B6: A | C6: Sci-Fi | D6: ☐ | E6: Genre Essential | F6: Original Master v1 — curated research basis
A7: Blank Generation | B7: A | C7: No Wave Cinema / Punk Drama / Downtown New York | D7: ☐ | E7: Cult Classic / Time Capsule / Music Cult | F7: SOURCE AUDIT NEEDED — final blind-spot pass
A8: Breaking Glass | B8: A | C8: Music / Punk / Drama | D8: ☐ | E8: Genre Essential | F8: SOURCE AUDIT NEEDED — row-level external source not retained
A9: Caddyshack | B9: A | C9: Sports Comedy / Ensemble | D9: ☐ | E9: Cult Canon | F9: SOURCE AUDIT NEEDED — row-level external source not retained
A10: Can't Stop the Music | B10: A | C10: Disco / Musical / Camp | D10: ☐ | E10: Camp Classic | F10: Original Master v1 — curated research basis
A11: Cannibal Apocalypse | B11: B | C11: Exploitation Horror | D11: ☐ | E11: Genre Deep Cut | F11: Original Master v1 — curated research basis
A12: Cannibal Holocaust | B12: A | C12: Exploitation | D12: ☐ | E12: Banned / Controversial | F12: Original Master v1 — curated research basis
... A64: Xanadu | B64: A | C64: Musical / Disco / Fantasy | D64: ☐ | E64: Camp Classic | F64: Original Master v1 — curated research basis
C66: In collectie | D66: =COUNTIF(D2:D64,"☑")&" / "&COUNTA(A2:A64) -> 0 / 63

Sheet 1981
A1: Title | B1: Priority | C1: Genre | D1: Status | E1: Curator Tags | F1: Source
A2: Alison's Birthday | B2: A | C2: Occult Horror | D2: ☐ | E2: Cult Canon | F2: https://www.nfsa.gov.au/stories/articles/survey-australian-horror-films-1970s-saw-and-babadook
A3: American Pop | B3: A | C3: Adult Animation / Music / Rotoscope | D3: ☐ | E3: Cult Canon | F3: https://www.imdb.com/title/tt0082009/
A4: Americana | B4: B | C4: Other / Unclassified | D4: ☐ | E4: Genre Deep Cut / Needs Genre Review | F4: Original Master v1 — curated research basis
A5: Bloody Birthday | B5: B | C5: Exploitation Horror | D5: ☐ | E5: Genre Deep Cut | F5: Original Master v1 — curated research basis
A6: Blow Out | B6: A | C6: Other / Unclassified | D6: ☐ | E6: Cult Canon / Needs Genre Review | F6: Original Master v1 — curated research basis
A7: Buddy Buddy | B7: B | C7: Other / Unclassified | D7: ☐ | E7: Genre Deep Cut / Needs Genre Review | F7: Original Master v1 — curated research basis
A8: Bustin' Loose | B8: A | C8: Black Comedy / Road / Family | D8: ☐ | E8: Genre Essential | F8: SOURCE AUDIT NEEDED — row-level external source not retained
A9: Carnival Magic | B9: B | C9: Other / Unclassified | D9: ☐ | E9: Genre Deep Cut / Needs Genre Review | F9: Original Master v1 — curated research basis
A10: Caveman | B10: B | C10: Other / Unclassified | D10: ☐ | E10: Genre Deep Cut / Needs Genre Review | F10: Original Master v1 — curated research basis
A11: Cutter's Way | B11: A | C11: Crime / Noir | D11: ☐ | E11: Rediscovered Cult | F11: Original Master v1 — curated research basis
A12: Dark Night of the Scarecrow | B12: A | C12: Made-for-TV Horror / Supernatural Revenge / Rural Horror | D12: ☐ | E12: TV Cult / Cult Classic | F12: SOURCE AUDIT NEEDED — final blind-spot pass
... A91: Zorro: The Gay Blade | B91: B | C91: Other / Unclassified | D91: ☐ | E91: Genre Deep Cut / Needs Genre Review | F91: Original Master v1 — curated research basis
C93: In collectie | D93: =COUNTIF(D2:D91,"☑")&" / "&COUNTA(A2:A91) -> 0 / 90

Sheet 1982
A1: Title | B1: Priority | C1: Genre | D1: Status | E1: Curator Tags | F1: Source
A2: 1990: The Bronx Warriors | B2: B | C2: Italian Post-Apocalyptic / Gang | D2: ☐ | E2: Genre Deep Cut | F2: https://en.wikipedia.org/wiki/1990%3A_The_Bronx_Warriors
A3: 48 Hrs. | B3: A | C3: Buddy Comedy / Action / Black Cinema | D3: ☐ | E3: Genre Essential | F3: SOURCE AUDIT NEEDED — row-level external source not retained
A4: Airplane II: The Sequel | B4: A | C4: Spoof / Parody / Sci-Fi Comedy | D4: ☐ | E4: Genre Essential | F4: SOURCE AUDIT NEEDED — row-level external source not retained
A5: Amityville II: The Possession | B5: B | C5: Other / Unclassified | D5: ☐ | E5: Genre Deep Cut / Needs Genre Review | F5: Original Master v1 — curated research basis
A6: Android | B6: A | C6: Sci-Fi | D6: ☐ | E6: Cult Canon | F6: Original Master v1 — curated research basis
A7: Ator, the Fighting Eagle | B7: A | C7: Sword & Sorcery / Italian Exploitation / Barbarian VHS | D7: ☐ | E7: VHS Classic / Cult Oddity | F7: https://www.cultcelebrities.com/sword-and-sorcery/
A8: Basket Case | B8: A | C8: Exploitation Horror | D8: ☐ | E8: Genre Essential | F8: Original Master v1 — curated research basis
A9: Battletruck / Warlords of the 21st Century | B9: A | C9: Post-Apocalyptic / Road Warrior Clone / Vehicles | D9: ☐ | E9: Genre Essential | F9: https://www.mondo-digital.com/bronxwarriors.html
A10: Best Friends | B10: B | C10: Other / Unclassified | D10: ☐ | E10: Genre Deep Cut / Needs Genre Review | F10: Original Master v1 — curated research basis
A11: Big Meat Eater | B11: B | C11: Other / Unclassified | D11: ☐ | E11: Genre Deep Cut / Needs Genre Review | F11: Original Master v1 — curated research basis
A12: Blade Runner | B12: C | C12: Tech-Noir Anchor / Cyberpunk / Future Noir | D12: ☐ | E12: Cult Canon / Canon Anchor / Genre Foundation | F12: https://www.bfi.org.uk/film/ec064a2a-f7a8-536a-afa2-ed076aad151f/blade-runner
... A85: Wolf Devil Woman | B85: B | C85: Exploitation Horror | D85: ☐ | E85: Genre Deep Cut | F85: Original Master v1 — curated research basis
C87: In collectie | D87: =COUNTIF(D2:D85,"☑")&" / "&COUNTA(A2:A85) -> 0 / 84

Sheet 1983
A1: Title | B1: Priority | C1: Genre | D1: Status | E1: Curator Tags | F1: Source
A2: 2019: After the Fall of New York | B2: A | C2: Italian Post-Nuke / Action | D2: ☐ | E2: Cult Canon | F2: https://www.mondo-digital.com/bronxwarriors.html
A3: 2020 Texas Gladiators | B3: A | C3: Italian Post-Nuke / Action / Mad Max Clone | D3: ☐ | E3: Genre Essential | F3: https://www.imdb.com/title/tt0083565/
A4: A Night in Heaven | B4: B | C4: Other / Unclassified | D4: ☐ | E4: Genre Deep Cut / Needs Genre Review | F4: Original Master v1 — curated research basis
A5: Attack of the Beast Creatures | B5: B | C5: Other / Unclassified | D5: ☐ | E5: Genre Deep Cut / Needs Genre Review | F5: Original Master v1 — curated research basis
A6: BMX Bandits | B6: B | C6: Australian Cult / Youth Action / Bikes | D6: ☐ | E6: Genre Deep Cut | F6: https://www.nfsa.gov.au/stories/articles/ozploitation-films-1970s-and-1980s
A7: Brainstorm | B7: A | C7: Sci-Fi | D7: ☐ | E7: Cult Canon | F7: Original Master v1 — curated research basis
A8: Cross Country | B8: B | C8: Other / Unclassified | D8: ☐ | E8: Genre Deep Cut / Needs Genre Review | F8: Original Master v1 — curated research basis
A9: Curtains | B9: A | C9: Slasher | D9: ☐ | E9: Cult Canon | F9: Original Master v1 — curated research basis
A10: Deathstalker | B10: A | C10: Sword & Sorcery / Corman / Barbarian Exploitation | D10: ☐ | E10: Cult Canon | F10: https://en.wikipedia.org/wiki/Deathstalker_(1983_film)
A11: Eddie And The Cruisers | B11: B | C11: Other / Unclassified | D11: ☐ | E11: Genre Deep Cut / Needs Genre Review | F11: Original Master v1 — curated research basis
A12: Educating Rita | B12: B | C12: Other / Unclassified | D12: ☐ | E12: Genre Deep Cut / Needs Genre Review | F12: Original Master v1 — curated research basis
... A75: Zu: Warriors from the Magic Mountain | B75: A | C75: Fantasy | D75: ☐ | E75: Cult Canon | F75: Original Master v1 — curated research basis
C77: In collectie | D77: =COUNTIF(D2:D75,"☑")&" / "&COUNTA(A2:A75) -> 0 / 74

Sheet 1984
A1: Title | B1: Priority | C1: Genre | D1: Status | E1: Curator Tags | F1: Source
A2: 1984 | B2: B | C2: Other / Unclassified | D2: ☐ | E2: Genre Deep Cut / Needs Genre Review | F2: Original Master v1 — curated research basis
A3: A Soldier's Story | B3: B | C3: Black Cinema / Mystery / Drama | D3: ☐ | E3: Genre Deep Cut | F3: Original Master v1 — curated research basis
A4: All of Me | B4: A | C4: Body-Swap Comedy / Fantasy | D4: ☐ | E4: Genre Essential | F4: SOURCE AUDIT NEEDED — row-level external source not retained
A5: Bachelor Party | B5: A | C5: Raunch Comedy / Party | D5: ☐ | E5: Cult Canon | F5: SOURCE AUDIT NEEDED — row-level external source not retained
A6: Beat Street | B6: A | C6: Hip-Hop / Dance / Music | D6: ☐ | E6: Genre Essential | F6: SOURCE AUDIT NEEDED — row-level external source not retained
A7: Black Devil Doll from Hell | B7: A | C7: Outsider Cinema / SOV Horror / Regional Underground | D7: ☐ | E7: SOV Cult / Regional Oddity / Psychotronic | F7: https://en.wikipedia.org/wiki/Black_Devil_Doll_from_Hell
A8: Blonde Death | B8: A | C8: Outsider Cinema / SOV Crime Comedy / Underground | D8: ☐ | E8: SOV Cult / Regional Oddity / Cult Oddity | F8: https://en.wikipedia.org/wiki/Blonde_Death
A9: Body Double | B9: A | C9: Thriller / Erotic | D9: ☐ | E9: Cult Canon | F9: Original Master v1 — curated research basis
A10: Body Rock | B10: B | C10: Dance / Music | D10: ☐ | E10: Genre Deep Cut | F10: SOURCE AUDIT NEEDED — row-level external source not retained
A11: Breakin' | B11: B | C11: Dance / Hip-Hop | D11: ☐ | E11: Genre Deep Cut | F11: Original Master v1 — curated research basis
A12: Breakin' 2: Electric Boogaloo | B12: A | C12: Dance / Hip-Hop / Camp | D12: ☐ | E12: Camp Classic | F12: SOURCE AUDIT NEEDED — row-level external source not retained
... A70: Wheels on Meals | B70: A | C70: Hong Kong Martial Arts / Jackie Chan / Sammo Hung / Action Comedy | D70: ☐ | E70: Genre Essential | F70: https://en.wikipedia.org/wiki/Wheels_on_Meals
C72: In collectie | D72: =COUNTIF(D2:D70,"☑")&" / "&COUNTA(A2:A70) -> 0 / 69

Sheet 1985
A1: Title | B1: Priority | C1: Genre | D1: Status | E1: Curator Tags | F1: Source
A2: After Hours | B2: A | C2: Surreal / Night Liminal / Dark Comedy | D2: ☐ | E2: Cult Canon | F2: https://www.criterion.com/films/29632-after-hours
A3: American Drive-In | B3: B | C3: Other / Unclassified | D3: ☐ | E3: Genre Deep Cut / Needs Genre Review | F3: Original Master v1 — curated research basis
A4: American Ninja | B4: A | C4: Ninja / Martial Arts VHS / Cannon | D4: ☐ | E4: VHS Classic | F4: https://editorial.rottentomatoes.com/article/top-ten-ninja-films/
A5: Baby: Secret of the Lost Legend | B5: A | C5: High-Concept Family / Video Store Cult / Dinosaur Adventure / Fantasy | D5: ☐ | E5: Forgotten Gem / Video Store Cult / Creature Feature | F5: SOURCE AUDIT NEEDED — high-concept family / video-store cult pass
A6: Back to the Future | B6: A | C6: Sci-Fi Comedy / Time Travel / Teen | D6: ☐ | E6: Genre Essential | F6: SOURCE AUDIT NEEDED — row-level external source not retained
A7: Barbarian Queen | B7: B | C7: Other / Unclassified | D7: ☐ | E7: Genre Deep Cut / Needs Genre Review | F7: Original Master v1 — curated research basis
A8: Better Off Dead | B8: A | C8: Dark Comedy / Comedy / Teen Comedy | D8: ☐ | E8: Cult Canon | F8: Original Master v1 — curated research basis
A9: Blood Cult | B9: A | C9: SOV Horror / Slasher / Home-Video Pioneer | D9: ☐ | E9: SOV Cult / VHS Classic / Genre Foundation | F9: https://www.americangenrefilm.com/theatrical-film-catalog/blood-cult/
A10: Brazil | B10: A | C10: Surreal / Bureaucratic Liminal / Retro-Futurist / Arthouse | D10: ☐ | E10: Genre Essential | F10: https://www.bfi.org.uk/film/bb840dfa-f69d-576b-bd99-dfa28efd4595/brazil
A11: Breaking All the Rules | B11: B | C11: Other / Unclassified | D11: ☐ | E11: Genre Deep Cut / Needs Genre Review | F11: Original Master v1 — curated research basis
A12: Brewster's Millions | B12: A | C12: High-Concept Comedy / Satire | D12: ☐ | E12: Genre Essential | F12: SOURCE AUDIT NEEDED — row-level external source not retained
... A99: Zone Troopers | B99: A | C99: Sci-Fi | D99: ☐ | E99: Genre Essential | F99: Original Master v1 — curated research basis
C101: In collectie | D101: =COUNTIF(D2:D99,"☑")&" / "&COUNTA(A2:A99) -> 0 / 98

Sheet 1986
A1: Title | B1: Priority | C1: Genre | D1: Status | E1: Curator Tags | F1: Source
A2: 8 Million Ways to Die | B2: B | C2: Other / Unclassified | D2: ☐ | E2: Genre Deep Cut / Needs Genre Review | F2: Original Master v1 — curated research basis
A3: A Better Tomorrow | B3: A | C3: Hong Kong Heroic Bloodshed / Gangster / Gunplay | D3: ☐ | E3: Cult Canon / Visual Cult | F3: https://www.bfi.org.uk/features/heroic-bloodshed-hong-kong-hollywood-cycle-influence
A4: About Last Night | B4: B | C4: Other / Unclassified | D4: ☐ | E4: Genre Deep Cut / Needs Genre Review | F4: Original Master v1 — curated research basis
A5: Absolute Beginners | B5: A | C5: Music / Musical / New Wave | D5: ☐ | E5: Genre Essential | F5: SOURCE AUDIT NEEDED — row-level external source not retained
A6: Amazons | B6: B | C6: Other / Unclassified | D6: ☐ | E6: Genre Deep Cut / Needs Genre Review | F6: Original Master v1 — curated research basis
A7: America 3000 | B7: A | C7: Post-Nuke / Barbarian / Camp | D7: ☐ | E7: Camp Classic | F7: https://www.mondo-digital.com/bronxwarriors.html
A8: Armed and Dangerous | B8: B | C8: Buddy Comedy / Action | D8: ☐ | E8: Genre Deep Cut | F8: SOURCE AUDIT NEEDED — row-level external source not retained
A9: Betty Blue | B9: B | C9: Other / Unclassified | D9: ☐ | E9: Genre Deep Cut / Needs Genre Review | F9: Original Master v1 — curated research basis
A10: Big Trouble in Little China | B10: A | C10: Action Comedy / Fantasy | D10: ☐ | E10: Cult Canon | F10: Original Master v1 — curated research basis
A11: Black Moon Rising | B11: B | C11: Neon Action / Supercar Techno-Thriller / 80s Cult | D11: ☐ | E11: Visual Cult | F11: https://www.imdb.com/title/tt0090735/
A12: Blood Hook | B12: B | C12: Exploitation Horror | D12: ☐ | E12: Genre Deep Cut | F12: Original Master v1 — curated research basis
... A85: Wildcats | B85: B | C85: Other / Unclassified | D85: ☐ | E85: Genre Deep Cut / Needs Genre Review | F85: Original Master v1 — curated research basis
C87: In collectie | D87: =COUNTIF(D2:D85,"☑")&" / "&COUNTA(A2:A85) -> 0 / 84

Sheet 1987
A1: Title | B1: Priority | C1: Genre | D1: Status | E1: Curator Tags | F1: Source
A2: 84 Charing Cross Road | B2: B | C2: Other / Unclassified | D2: ☐ | E2: Genre Deep Cut / Needs Genre Review | F2: Original Master v1 — curated research basis
A3: A Better Tomorrow II | B3: B | C3: Hong Kong Heroic Bloodshed / Gangster / Gunplay / Sequel | D3: ☐ | E3: Genre Deep Cut | F3: https://www.bfi.org.uk/features/heroic-bloodshed-hong-kong-hollywood-cycle-influence
A4: Adventures in Babysitting | B4: B | C4: Other / Unclassified | D4: ☐ | E4: Genre Deep Cut / Needs Genre Review | F4: Original Master v1 — curated research basis
A5: Amazon Women on the Moon | B5: B | C5: Spoof / Sketch Comedy | D5: ☐ | E5: Genre Deep Cut | F5: Original Master v1 — curated research basis
A6: American Ninja 2: The Confrontation | B6: B | C6: Ninja / Martial Arts VHS / Cannon / Sequel | D6: ☐ | E6: VHS Classic | F6: https://editorial.rottentomatoes.com/article/top-ten-ninja-films/
A7: Baby Boom | B7: B | C7: Other / Unclassified | D7: ☐ | E7: Genre Deep Cut / Needs Genre Review | F7: Original Master v1 — curated research basis
A8: Bad Taste | B8: A | C8: Other / Unclassified | D8: ☐ | E8: Cult Canon / Needs Genre Review | F8: Original Master v1 — curated research basis
A9: Banzai Runner | B9: B | C9: Other / Unclassified | D9: ☐ | E9: Genre Deep Cut / Needs Genre Review | F9: Original Master v1 — curated research basis
A10: Benji the Hunted | B10: B | C10: Family Animal Adventure / Wilderness / Survival | D10: ☐ | E10: Genre Deep Cut | F10: https://en.wikipedia.org/wiki/Benji_the_Hunted
A11: Berserker | B11: B | C11: Other / Unclassified | D11: ☐ | E11: Genre Deep Cut / Needs Genre Review | F11: Original Master v1 — curated research basis
A12: Blind Date | B12: B | C12: Other / Unclassified | D12: ☐ | E12: Genre Deep Cut / Needs Genre Review | F12: Original Master v1 — curated research basis
... A90: Withnail and I | B90: A | C90: Other / Unclassified | D90: ☐ | E90: Cult Canon / Needs Genre Review | F90: Original Master v1 — curated research basis
C92: In collectie | D92: =COUNTIF(D2:D90,"☑")&" / "&COUNTA(A2:A90) -> 0 / 89

Sheet 1988
A1: Title | B1: Priority | C1: Genre | D1: Status | E1: Curator Tags | F1: Source
A2: 18 Again! | B2: B | C2: Body-Swap Comedy / Fantasy | D2: ☐ | E2: Genre Deep Cut | F2: SOURCE AUDIT NEEDED — row-level external source not retained
A3: 555 | B3: A | C3: SOV Horror / Slasher / Regional Underground | D3: ☐ | E3: SOV Cult / Rare VHS / Regional Oddity | F3: https://en.wikipedia.org/wiki/555_(film)
A4: A Fish Called Wanda | B4: A | C4: Crime Comedy / Farce | D4: ☐ | E4: Genre Essential | F4: SOURCE AUDIT NEEDED — row-level external source not retained
A5: Akira | B5: C | C5: Adult Animation Anchor / Cyberpunk / Anime | D5: ☐ | E5: Cult Canon / Canon Anchor | F5: https://www.bfi.org.uk/sight-and-sound/lists/50-key-anime-films
A6: Alien Nation | B6: B | C6: Sci-Fi | D6: ☐ | E6: Genre Deep Cut | F6: Original Master v1 — curated research basis
A7: Beetlejuice | B7: A | C7: Surreal / Afterlife Bureaucracy / Artificial World | D7: ☐ | E7: Cult Canon | F7: https://www.bfi.org.uk/lists/top-your-watchlist-23-cult-films-1980s
A8: Big | B8: A | C8: Fantasy Comedy / High-Concept | D8: ☐ | E8: Genre Essential | F8: SOURCE AUDIT NEEDED — row-level external source not retained
A9: Bloodsport | B9: C | C9: Martial Arts VHS Anchor / Tournament / Van Damme | D9: ☐ | E9: Cult Canon / Canon Anchor / VHS Classic | F9: https://en.wikipedia.org/wiki/Bloodsport_(film)
A10: Brain Damage | B10: A | C10: Other / Unclassified | D10: ☐ | E10: Cult Canon / Needs Genre Review | F10: Original Master v1 — curated research basis
A11: Cannibal Campout | B11: A | C11: SOV Horror / Backwoods Splatter / Regional Cult | D11: ☐ | E11: SOV Cult / VHS Classic / Regional Oddity | F11: https://en.wikipedia.org/wiki/Cannibal_Campout
A12: Coming to America | B12: A | C12: Black Comedy / Romance | D12: ☐ | E12: Cult Canon | F12: SOURCE AUDIT NEEDED — row-level external source not retained
... A58: World Gone Wild | B58: A | C58: Post-Apocalyptic / Western | D58: ☐ | E58: Cult Canon | F58: https://www.mondo-digital.com/bronxwarriors.html
C60: In collectie | D60: =COUNTIF(D2:D58,"☑")&" / "&COUNTA(A2:A58) -> 0 / 57

Sheet 1989
A1: Title | B1: Priority | C1: Genre | D1: Status | E1: Curator Tags | F1: Source
A2: Arena | B2: A | C2: Sci-Fi / Creature Feature | D2: ☐ | E2: DTV Cult / Creature Feature | F2: Original Master v1 — curated research basis
A3: Bill & Ted's Excellent Adventure | B3: A | C3: Sci-Fi Comedy / Time Travel / Teen | D3: ☐ | E3: Genre Essential | F3: SOURCE AUDIT NEEDED — row-level external source not retained
A4: Black Past | B4: A | C4: Other / Unclassified | D4: ☐ | E4: DTV Cult / SOV Cult / Needs Genre Review | F4: Original Master v1 — curated research basis
A5: Cheetah | B5: A | C5: Family Animal Adventure / Kids Adventure / Africa | D5: ☐ | E5: Cult Canon | F5: https://movies.disney.com/cheetah
A6: Communion | B6: A | C6: Alien Abduction / Psychological Sci-Fi / UFO Cult | D6: ☐ | E6: Cult Classic / Cult Oddity | F6: https://en.wikipedia.org/wiki/Communion_(1989_film)
A7: Cyborg | B7: B | C7: Neo-80s Action / Post-Apocalyptic Martial Arts / Cannon Cult | D7: ☐ | E7: VHS Classic | F7: https://www.imdb.com/title/tt0097138/
A8: Dead Calm | B8: C | C8: Australian Thriller Anchor / Maritime | D8: ☐ | E8: Canon Anchor | F8: https://www.nfsa.gov.au/stories/articles/survey-australian-horror-films-1970s-saw-and-babadook
A9: Do the Right Thing | B9: A | C9: Black Cinema / Comedy-Drama / Urban | D9: ☐ | E9: Genre Essential | F9: SOURCE AUDIT NEEDED — row-level external source not retained
A10: Dr. Caligari | B10: A | C10: Arthouse / Surreal | D10: ☐ | E10: Cult Canon | F10: Original Master v1 — curated research basis
A11: Dream a Little Dream | B11: A | C11: Teen Fantasy / Body-Swap | D11: ☐ | E11: Cult Canon | F11: SOURCE AUDIT NEEDED — row-level external source not retained
A12: Drugstore Cowboy | B12: A | C12: Crime | D12: ☐ | E12: Cult Canon | F12: Original Master v1 — curated research basis
... A49: Weekend at Bernie's | B49: A | C49: Dark Comedy / Farce | D49: ☐ | E49: Cult Canon | F49: SOURCE AUDIT NEEDED — row-level external source not retained
C51: In collectie | D51: =COUNTIF(D2:D49,"☑")&" / "&COUNTA(A2:A49) -> 0 / 48

Sheet 1990
A1: Title | B1: Priority | C1: Genre | D1: Status | E1: Curator Tags | F1: Source
A2: Aftershock | B2: A | C2: Post-Apocalyptic / Martial Arts | D2: ☐ | E2: DTV Cult | F2: https://en.wikipedia.org/wiki/Aftershock_%281990_film%29
A3: Basket Case 2 | B3: A | C3: Other / Unclassified | D3: ☐ | E3: Cult Canon / Needs Genre Review | F3: Original Master v1 — curated research basis
A4: Brain Dead | B4: A | C4: Sci-Fi | D4: ☐ | E4: Cult Canon | F4: Original Master v1 — curated research basis
A5: Bullet in the Head | B5: A | C5: Hong Kong Heroic Bloodshed / War Crime / Brotherhood | D5: ☐ | E5: Cult Canon | F5: https://www.bfi.org.uk/features/heroic-bloodshed-hong-kong-hollywood-cycle-influence
A6: China O'Brien | B6: A | C6: Martial Arts VHS / Cynthia Rothrock / DTV Cult | D6: ☐ | E6: VHS Classic / DTV Cult | F6: https://en.wikipedia.org/wiki/China_O%27Brien
A7: Circuitry Man | B7: A | C7: Neon Cyberpunk / Post-Apocalyptic Road Movie / Indie Cult | D7: ☐ | E7: Visual Cult | F7: https://en.wikipedia.org/wiki/Circuitry_Man
A8: Class of 1999 | B8: A | C8: Neon Action / Cyberpunk School / Killer Androids | D8: ☐ | E8: Visual Cult | F8: https://www.imdb.com/title/tt0099277/
A9: Crash and Burn | B9: A | C9: Sci-Fi | D9: ☐ | E9: DTV Cult | F9: Original Master v1 — curated research basis
A10: Cry-Baby | B10: A | C10: Musical / Teen / Rockabilly | D10: ☐ | E10: Cult Canon | F10: SOURCE AUDIT NEEDED — row-level external source not retained
A11: Darkman | B11: A | C11: Superhero | D11: ☐ | E11: Cult Canon | F11: Original Master v1 — curated research basis
A12: Demon Wind | B12: A | C12: Horror — Subgenre Review | D12: ☐ | E12: VHS Classic | F12: Original Master v1 — curated research basis
... A51: Troll 2 | B51: A | C51: Outsider Fantasy Horror / Goblin Horror / Amateur Cult | D51: ☐ | E51: So-Bad-It's-Good / Cult Canon / Cult Oddity | F51: https://en.wikipedia.org/wiki/Troll_2
C53: In collectie | D53: =COUNTIF(D2:D51,"☑")&" / "&COUNTA(A2:A51) -> 0 / 50

Sheet 1991
A1: Title | B1: Priority | C1: Genre | D1: Status | E1: Curator Tags | F1: Source
A2: 964 Pinocchio | B2: A | C2: Body Horror | D2: ☐ | E2: Cult Canon | F2: https://en.wikipedia.org/wiki/Japanese_cyberpunk
A3: A Rage in Harlem | B3: A | C3: Black Crime Comedy / Noir | D3: ☐ | E3: Genre Essential | F3: SOURCE AUDIT NEEDED — row-level external source not retained
A4: Barton Fink | B4: A | C4: Hotel Liminal / Surreal / Arthouse / Dark Comedy | D4: ☐ | E4: Genre Essential | F4: https://www.bfi.org.uk/lists/top-your-watchlist-23-cult-films-1980s
A5: Bingo | B5: B | C5: High-Concept Family / Video Store Cult / Animal Adventure / Comedy | D5: ☐ | E5: Forgotten Gem / Video Store Cult / Family Oddity | F5: SOURCE AUDIT NEEDED — high-concept family / video-store cult pass
A6: Campfire Tales | B6: B | C6: Other / Unclassified | D6: ☐ | E6: DTV Cult / Needs Genre Review | F6: Original Master v1 — curated research basis
A7: Cool as Ice | B7: A | C7: Comedy / Camp / Music | D7: ☐ | E7: Camp Classic | F7: Original Master v1 — curated research basis
A8: Critters 3 | B8: A | C8: Other / Unclassified | D8: ☐ | E8: DTV Cult / Needs Genre Review | F8: Original Master v1 — curated research basis
A9: Delicatessen | B9: A | C9: Artificial World / Surreal / Dark Comedy / Arthouse | D9: ☐ | E9: Genre Essential | F9: https://www.bfi.org.uk/lists/top-your-watchlist-23-cult-films-1980s
A10: Dollman | B10: A | C10: Sci-Fi / Action | D10: ☐ | E10: DTV Cult | F10: Original Master v1 — curated research basis
A11: Drop Dead Fred | B11: A | C11: Fantasy Comedy / Dark Comedy | D11: ☐ | E11: Cult Canon | F11: SOURCE AUDIT NEEDED — row-level external source not retained
A12: Dune Warriors | B12: A | C12: Post-Apocalyptic / Corman / Philippine DTV | D12: ☐ | E12: DTV Cult | F12: https://en.wikipedia.org/wiki/Dune_Warriors
... A47: White Fang | B47: B | C47: Family Animal Adventure / Coming-of-Age / Wilderness | D47: ☐ | E47: Genre Deep Cut | F47: https://movies.disney.com/white-fang
C49: In collectie | D49: =COUNTIF(D2:D47,"☑")&" / "&COUNTA(A2:A47) -> 0 / 46

Sheet 1992
A1: Title | B1: Priority | C1: Genre | D1: Status | E1: Curator Tags | F1: Source
A2: 3 Ninjas | B2: A | C2: High-Concept Family / Video Store Cult / Kids Action / Martial Arts | D2: ☐ | E2: Forgotten Gem / Video Store Cult / High-Concept | F2: SOURCE AUDIT NEEDED — row-level external source not retained
A3: 976-EVIL II | B3: A | C3: TV Horror | D3: ☐ | E3: DTV Cult | F3: Original Master v1 — curated research basis
A4: Bad Channels | B4: A | C4: Sci-Fi / Comedy | D4: ☐ | E4: DTV Cult | F4: Original Master v1 — curated research basis
A5: Bad Lieutenant | B5: A | C5: Other / Unclassified | D5: ☐ | E5: Cult Canon / Needs Genre Review | F5: Original Master v1 — curated research basis
A6: Basket Case 3: The Progeny | B6: A | C6: Other / Unclassified | D6: ☐ | E6: Cult Canon / Needs Genre Review | F6: Original Master v1 — curated research basis
A7: Bob Roberts | B7: A | C7: Mockumentary / Political Satire / Folk Music | D7: ☐ | E7: Camp Classic | F7: https://en.wikipedia.org/wiki/Bob_Roberts
A8: Boomerang | B8: A | C8: Black Romantic Comedy | D8: ☐ | E8: Cult Canon | F8: SOURCE AUDIT NEEDED — row-level external source not retained
A9: Brain Donors | B9: A | C9: Slapstick / Marx Brothers Homage | D9: ☐ | E9: Cult Canon | F9: SOURCE AUDIT NEEDED — row-level external source not retained
A10: Braindead / Dead Alive | B10: A | C10: Other / Unclassified | D10: ☐ | E10: Cult Canon / Needs Genre Review | F10: Original Master v1 — curated research basis
A11: CB4 | B11: A | C11: Black Comedy / Music Satire | D11: ☐ | E11: Cult Canon | F11: SOURCE AUDIT NEEDED — row-level external source not retained
A12: Cool World | B12: A | C12: Adult Animation / Live-Action Hybrid / Dark Fantasy | D12: ☐ | E12: Notorious Flop / Cult Oddity | F12: https://www.imdb.com/title/tt0104009/
... A49: White Men Can't Jump | B49: A | C49: Black Comedy / Sports / Buddy | D49: ☐ | E49: Genre Essential | F49: SOURCE AUDIT NEEDED — row-level external source not retained
C51: In collectie | D51: =COUNTIF(D2:D49,"☑")&" / "&COUNTA(A2:A49) -> 0 / 48

Sheet 1993
A1: Title | B1: Priority | C1: Genre | D1: Status | E1: Curator Tags | F1: Source
A2: American Cyborg: Steel Warrior | B2: A | C2: Post-Apocalyptic / Cannon / Cyborg Action | D2: ☐ | E2: Genre Essential | F2: https://en.wikipedia.org/wiki/American_Cyborg%3A_Steel_Warrior
A3: Amityville: A New Generation | B3: A | C3: Horror — Subgenre Review | D3: ☐ | E3: DTV Cult | F3: Original Master v1 — curated research basis
A4: Arcade | B4: A | C4: Neon Cyber / Virtual Reality / Full Moon | D4: ☐ | E4: Visual Cult | F4: https://www.imdb.com/title/tt0106302/
A5: Body Snatchers | B5: A | C5: Sci-Fi Horror | D5: ☐ | E5: Cult Canon | F5: Original Master v1 — curated research basis
A6: Boxing Helena | B6: A | C6: Thriller / Erotic | D6: ☐ | E6: Banned / Controversial | F6: Original Master v1 — curated research basis
A7: Cemetery Man / Dellamorte Dellamore | B7: A | C7: Italian Horror | D7: ☐ | E7: Cult Canon | F7: Original Master v1 — curated research basis
A8: Champagne and Bullets | B8: A | C8: Outsider Action / Vanity Project / Crime | D8: ☐ | E8: So-Bad-It's-Good / Cult Oddity / Regional Oddity | F8: https://en.wikipedia.org/wiki/Champagne_and_Bullets
A9: Cop and a Half | B9: B | C9: High-Concept Family / Video Store Cult / Buddy Cop / Kids Comedy | D9: ☐ | E9: Forgotten Gem / Video Store Cult / Star Vehicle | F9: SOURCE AUDIT NEEDED — high-concept family / video-store cult pass
A10: Cronos | B10: A | C10: Horror — Subgenre Review | D10: ☐ | E10: Genre Essential | F10: Original Master v1 — curated research basis
A11: Cyborg 2 | B11: B | C11: Dystopian / Cyberpunk | D11: ☐ | E11: DTV Cult | F11: https://www.mondo-digital.com/bronxwarriors.html
A12: Dark Waters | B12: A | C12: Folk Horror / Occult Horror / Cosmic Horror | D12: ☐ | E12: Cult Canon | F12: https://en.wikipedia.org/wiki/Dark_Waters_(1993_film)
... A46: What's Love Got to Do with It | B46: A | C46: Music / Biopic / Drama | D46: ☐ | E46: Genre Essential | F46: SOURCE AUDIT NEEDED — row-level external source not retained
C48: In collectie | D48: =COUNTIF(D2:D46,"☑")&" / "&COUNTA(A2:A46) -> 2 / 45

Sheet 1994
A1: Title | B1: Priority | C1: Genre | D1: Status | E1: Curator Tags | F1: Source
A2: 3 Ninjas Kick Back | B2: B | C2: Forgotten Family / Kids Action / Martial Arts | D2: ☐ | E2: Forgotten Gem | F2: SOURCE AUDIT NEEDED — row-level external source not retained
A3: A Low Down Dirty Shame | B3: B | C3: Black Action Comedy / Detective | D3: ☐ | E3: Genre Deep Cut | F3: SOURCE AUDIT NEEDED — row-level external source not retained
A4: A Troll in Central Park | B4: B | C4: Forgotten Family / Animation / Fantasy | D4: ☐ | E4: Forgotten Gem | F4: SOURCE AUDIT NEEDED — row-level external source not retained
A5: Airheads | B5: A | C5: Music / Comedy | D5: ☐ | E5: Cult Canon | F5: SOURCE AUDIT NEEDED — row-level external source not retained
A6: Amityville: Dollhouse | B6: A | C6: Horror — Subgenre Review | D6: ☐ | E6: DTV Cult | F6: Original Master v1 — curated research basis
A7: Andre | B7: B | C7: Family Animal Adventure / Kids Drama / Seal | D7: ☐ | E7: Forgotten Gem | F7: https://www.imdb.com/title/tt0109120/
A8: Baby's Day Out | B8: B | C8: Forgotten Family / Comedy / Kids Adventure | D8: ☐ | E8: Forgotten Gem | F8: SOURCE AUDIT NEEDED — row-level external source not retained
A9: Black Beauty | B9: B | C9: Family Animal Adventure / Horse Drama / Period | D9: ☐ | E9: Genre Deep Cut | F9: https://en.wikipedia.org/wiki/Black_Beauty_%281994_film%29
A10: Blank Check | B10: A | C10: High-Concept Family / Video Store Cult / Wish-Fulfilment Comedy | D10: ☐ | E10: Forgotten Gem / Video Store Cult / High-Concept | F10: SOURCE AUDIT NEEDED — row-level external source not retained
A11: Brainscan | B11: A | C11: Horror — Subgenre Review | D11: ☐ | E11: Visual Cult | F11: https://www.imdb.com/title/tt0109327/
A12: Camp Nowhere | B12: A | C12: Forgotten Family / Kids Adventure / Summer Camp | D12: ☐ | E12: Camp Classic / Forgotten Gem | F12: SOURCE AUDIT NEEDED — row-level external source not retained
... A60: White Fang 2: Myth of the White Wolf | B60: B | C60: Family Animal Adventure / Wilderness / Forgotten Sequel | D60: ☐ | E60: VHS Classic / Forgotten Gem | F60: https://en.wikipedia.org/wiki/White_Fang_2%3A_Myth_of_the_White_Wolf
C62: In collectie | D62: =COUNTIF(D2:D60,"☑")&" / "&COUNTA(A2:A60) -> 3 / 59

Sheet 1995
A1: Title | B1: Priority | C1: Genre | D1: Status | E1: Curator Tags | F1: Source
A2: 12 Monkeys | B2: C | C2: Time Travel / Dystopian Sci-Fi / Pandemic Thriller | D2: ☐ | E2: Canon Anchor / Genre Essential | F2: https://en.wikipedia.org/wiki/12_Monkeys
A3: 3 Ninjas Knuckle Up | B3: B | C3: Forgotten Family / Kids Action / Martial Arts | D3: ☐ | E3: Forgotten Gem | F3: SOURCE AUDIT NEEDED — row-level external source not retained
A4: A Kid in King Arthur's Court | B4: B | C4: Forgotten Family / Kids Fantasy / Time Travel | D4: ☐ | E4: Forgotten Gem | F4: SOURCE AUDIT NEEDED — row-level external source not retained
A5: Automatic | B5: A | C5: Neon Action / Android / DTV Cyberpunk | D5: ☐ | E5: DTV Cult / Visual Cult | F5: https://www.imdb.com/title/tt0112426/
A6: Born to Be Wild | B6: A | C6: Family Animal Adventure / Kids Drama / Gorilla / Road Movie | D6: ☐ | E6: Genre Essential | F6: https://www.imdb.com/title/tt0113533/
A7: Bushwhacked | B7: B | C7: High-Concept Family / Video Store Cult / Kids Adventure / Crime Comedy | D7: ☐ | E7: Forgotten Gem / Video Store Cult / Star Vehicle | F7: SOURCE AUDIT NEEDED — high-concept family / video-store cult pass
A8: Castle Freak | B8: A | C8: Other / Unclassified | D8: ☐ | E8: DTV Cult / Needs Genre Review | F8: Original Master v1 — curated research basis
A9: CyberTracker 2 | B9: A | C9: Sci-Fi / Cyberpunk / Action / Music | D9: ☐ | E9: DTV Cult | F9: Original Master v1 — curated research basis
A10: Dead Man | B10: A | C10: Western | D10: ☐ | E10: Cult Canon | F10: Original Master v1 — curated research basis
A11: Demon Knight | B11: A | C11: Horror — Subgenre Review | D11: ☐ | E11: Cult Canon | F11: Original Master v1 — curated research basis
A12: Dracula: Dead and Loving It | B12: B | C12: Horror — Subgenre Review | D12: ☐ | E12: Genre Deep Cut | F12: SOURCE AUDIT NEEDED — row-level external source not retained
... A66: Welcome to the Dollhouse | B66: A | C66: 90s Indie / Dark Coming-of-Age / Suburban Cruelty | D66: ☐ | E66: Genre Essential | F66: https://en.wikipedia.org/wiki/Welcome_to_the_Dollhouse
C68: In collectie | D68: =COUNTIF(D2:D66,"☑")&" / "&COUNTA(A2:A66) -> 1 / 65

Sheet 1996
A1: Title | B1: Priority | C1: Genre | D1: Status | E1: Curator Tags | F1: Source
A2: Adrenalin: Fear the Rush | B2: A | C2: Sci-Fi / Action | D2: ☐ | E2: DTV Cult | F2: Original Master v1 — curated research basis
A3: Alaska | B3: A | C3: Family Animal Adventure / Kids Survival / Polar Bear | D3: ☐ | E3: Genre Essential | F3: https://en.wikipedia.org/wiki/Alaska_%281996_film%29
A4: Bad Moon | B4: A | C4: Werewolf Horror | D4: ☐ | E4: Cult Canon | F4: Original Master v1 — curated research basis
A5: Barb Wire | B5: A | C5: Comedy / Camp | D5: ☐ | E5: Camp Classic | F5: https://www.mondo-digital.com/bronxwarriors.html
A6: Bogus | B6: B | C6: Forgotten Family / Fantasy Drama / Kids | D6: ☐ | E6: Forgotten Gem | F6: SOURCE AUDIT NEEDED — row-level external source not retained
A7: Bound | B7: A | C7: Crime / Noir | D7: ☐ | E7: Cult Canon | F7: Original Master v1 — curated research basis
A8: Cannibal! The Musical | B8: A | C8: Music | D8: ☐ | E8: Genre Essential | F8: Original Master v1 — curated research basis
A9: Crash | B9: A | C9: Arthouse | D9: ☐ | E9: Cult Canon | F9: Original Master v1 — curated research basis
A10: Digital Man | B10: A | C10: Neon Action / Cyborg / DTV Sci-Fi | D10: ☐ | E10: VHS Classic / DTV Cult / Visual Cult | F10: https://www.imdb.com/title/tt0112867/
A11: Doctor Mordrid | B11: A | C11: Fantasy | D11: ☐ | E11: Cult Canon | F11: Original Master v1 — curated research basis
A12: Don't Be a Menace to South Central While Drinking Your Juice in the Hood | B12: A | C12: Black Comedy / Spoof / Parody | D12: ☐ | E12: Genre Essential | F12: SOURCE AUDIT NEEDED — row-level external source not retained
... A55: Waiting for Guffman | B55: A | C55: Mockumentary / Community Theatre / Christopher Guest | D55: ☐ | E55: Genre Essential | F55: https://en.wikipedia.org/wiki/Waiting_for_Guffman
C57: In collectie | D57: =COUNTIF(D2:D55,"☑")&" / "&COUNTA(A2:A55) -> 0 / 54

Sheet 1997
A1: Title | B1: Priority | C1: Genre | D1: Status | E1: Curator Tags | F1: Source
A2: A Simple Wish | B2: A | C2: Forgotten Family / Fantasy Comedy / Kids Adventure | D2: ☐ | E2: Forgotten Gem | F2: SOURCE AUDIT NEEDED — row-level external source not retained
A3: Air Bud | B3: B | C3: Family Animal Adventure / Kids Sports / Dog | D3: ☐ | E3: Genre Deep Cut | F3: https://www.imdb.com/title/tt0118570/
A4: Alien Escape | B4: A | C4: Sci-Fi Horror | D4: ☐ | E4: DTV Cult | F4: Original Master v1 — curated research basis
A5: Austin Powers: International Man of Mystery | B5: A | C5: Spy Spoof / Parody | D5: ☐ | E5: Cult Canon | F5: SOURCE AUDIT NEEDED — row-level external source not retained
A6: B*A*P*S | B6: A | C6: Black Comedy / Camp | D6: ☐ | E6: Camp Classic | F6: SOURCE AUDIT NEEDED — row-level external source not retained
A7: Booty Call | B7: B | C7: Black Comedy / Sex Comedy | D7: ☐ | E7: Genre Deep Cut | F7: SOURCE AUDIT NEEDED — row-level external source not retained
A8: Contact | B8: C | C8: First Contact / Philosophical Sci-Fi / SETI | D8: ☐ | E8: Canon Anchor / Genre Essential | F8: https://en.wikipedia.org/wiki/Contact_(1997_American_film)
A9: Cube | B9: A | C9: Sci-Fi Horror | D9: ☐ | E9: Cult Canon | F9: https://www.bfi.org.uk/lists/top-your-watchlist-23-cult-films-1980s
A10: Cure | B10: A | C10: Psychological Horror / Crime / Hypnotic Horror / Urban Dread | D10: ☐ | E10: Cult Canon / Genre Essential / J-Horror Precursor | F10: https://www.bfi.org.uk/lists/10-great-films-1997
A11: Dobermann | B11: A | C11: Action | D11: ☐ | E11: Cult Canon | F11: Original Master v1 — curated research basis
A12: Drive | B12: A | C12: Neon Action / Cyber-Enhanced Martial Arts / DTV Cult | D12: ☐ | E12: VHS Classic / DTV Cult / Visual Cult | F12: https://en.wikipedia.org/wiki/Drive_(1997_film)
... A47: Zeus and Roxanne | B47: B | C47: Family Animal Adventure / Kids Comedy / Dog & Dolphin | D47: ☐ | E47: Forgotten Gem | F47: https://www.imdb.com/title/tt0120550/
C49: In collectie | D49: =COUNTIF(D2:D47,"☑")&" / "&COUNTA(A2:A47) -> 0 / 46

Sheet 1998
A1: Title | B1: Priority | C1: Genre | D1: Status | E1: Curator Tags | F1: Source
A2: 3 Ninjas: High Noon at Mega Mountain | B2: B | C2: Forgotten Family / Kids Action / Martial Arts / DTV-era | D2: ☐ | E2: DTV Cult / Forgotten Gem | F2: SOURCE AUDIT NEEDED — row-level external source not retained
A3: BASEketball | B3: A | C3: Sports Comedy / Absurdist | D3: ☐ | E3: Cult Canon | F3: SOURCE AUDIT NEEDED — row-level external source not retained
A4: Blade | B4: B | C4: Action | D4: ☐ | E4: Genre Deep Cut | F4: Original Master v1 — curated research basis
A5: Bride of Chucky | B5: B | C5: Horror Comedy | D5: ☐ | E5: Camp Classic | F5: Original Master v1 — curated research basis
A6: Buffalo '66 | B6: A | C6: Other / Unclassified | D6: ☐ | E6: Cult Canon / Needs Genre Review | F6: Original Master v1 — curated research basis
A7: Children of the Corn V: Fields of Terror | B7: A | C7: Horror — Subgenre Review | D7: ☐ | E7: DTV Cult | F7: Original Master v1 — curated research basis
A8: Curse of the Puppet Master | B8: A | C8: Other / Unclassified | D8: ☐ | E8: DTV Cult / Needs Genre Review | F8: Original Master v1 — curated research basis
A9: Dark City | B9: A | C9: Tech-Noir / Artificial City / Neo-Noir / Sci-Fi Cult | D9: ☐ | E9: Cult Canon | F9: https://www.imdb.com/title/tt0118929/
A10: Fear and Loathing in Las Vegas | B10: A | C10: Other / Unclassified | D10: ☐ | E10: Cult Canon / Needs Genre Review | F10: Original Master v1 — curated research basis
A11: Half Baked | B11: A | C11: Stoner Comedy / Black Comedy | D11: ☐ | E11: Cult Canon | F11: SOURCE AUDIT NEEDED — row-level external source not retained
A12: Happiness | B12: A | C12: Dark Comedy / Comedy | D12: ☐ | E12: Genre Essential | F12: Original Master v1 — curated research basis
... A36: Velvet Goldmine | B36: A | C36: Music / Glam Rock / Arthouse | D36: ☐ | E36: Cult Canon | F36: Original Master v1 — curated research basis
C38: In collectie | D38: =COUNTIF(D2:D36,"☑")&" / "&COUNTA(A2:A36) -> 0 / 35

Sheet 1999
A1: Title | B1: Priority | C1: Genre | D1: Status | E1: Curator Tags | F1: Source
A2: Audition | B2: A | C2: Psychological Horror / Relationship Horror / Extreme Horror | D2: ☐ | E2: Cult Canon / Genre Essential | F2: Original Master v1 — curated research basis
A3: Austin Powers: The Spy Who Shagged Me | B3: A | C3: Spy Spoof / Parody | D3: ☐ | E3: Cult Canon | F3: SOURCE AUDIT NEEDED — row-level external source not retained
A4: Being John Malkovich | B4: A | C4: Surreal / Office Liminal / Dark Comedy | D4: ☐ | E4: Cult Canon | F4: https://www.bfi.org.uk/film/bb840dfa-f69d-576b-bd99-dfa28efd4595/brazil
A5: Blood Dolls | B5: A | C5: TV Horror | D5: ☐ | E5: DTV Cult | F5: Original Master v1 — curated research basis
A6: But I'm a Cheerleader | B6: A | C6: Comedy / Camp | D6: ☐ | E6: Camp Classic | F6: Original Master v1 — curated research basis
A7: Children of the Corn 666: Isaac's Return | B7: A | C7: Horror — Subgenre Review | D7: ☐ | E7: DTV Cult | F7: Original Master v1 — curated research basis
A8: Detroit Rock City | B8: A | C8: Music / Teen / Comedy | D8: ☐ | E8: Cult Canon | F8: Original Master v1 — curated research basis
A9: eXistenZ | B9: A | C9: Tech-Noir Adjacent / Biopunk / Artificial Reality | D9: ☐ | E9: Cult Canon | F9: https://www.imdb.com/title/tt0120907/
A10: Eyes Wide Shut | B10: C | C10: Other / Unclassified | D10: ☐ | E10: Cult Canon / Canon Anchor / Needs Genre Review | F10: Original Master v1 — curated research basis
A11: Galaxy Quest | B11: B | C11: Sci-Fi / Comedy | D11: ☐ | E11: Genre Deep Cut | F11: Original Master v1 — curated research basis
A12: Ghost Dog: The Way of the Samurai | B12: A | C12: Crime | D12: ☐ | E12: Cult Canon | F12: Original Master v1 — curated research basis
... A32: Velocity Trap | B32: A | C32: Sci-Fi / Action | D32: ☐ | E32: DTV Cult | F32: Original Master v1 — curated research basis
C34: In collectie | D34: =COUNTIF(D2:D32,"☑")&" / "&COUNTA(A2:A32) -> 0 / 31

Sheet Pre-1960
A1: Title | B1: Year | C1: Priority | D1: Genre | E1: Status | F1: Curator Tags | G1: Source
A2: A Trip to the Moon | B2: 1902 | C2: A | D2: Pre-1960 Foundation / Sci-Fi / Trick Film / Surreal | E2: ☐ | F2: Genre Foundation / Practical FX Showcase | G2: https://www.bfi.org.uk/features/where-begin-georges-melies
A3: The Cabinet of Dr. Caligari | B3: 1920 | C3: A | D3: Horror — Subgenre Review | E3: ☐ | F3: Genre Foundation / Genre Essential | G3: https://www.bfi.org.uk/features/100-years-cabinet-dr-caligari
A4: The Golem: How He Came into the World | B4: 1920 | C4: A | D4: Eco / Creature Horror | E4: ☐ | F4: Genre Foundation / Creature Feature / Visual Cult | G4: https://www.bfi.org.uk/lists/10-great-german-horror-films
A5: Häxan | B5: 1922 | C5: A | D5: Occult Horror | E5: ☐ | F5: Genre Foundation | G5: https://www.bfi.org.uk/lists/great-horror-film-from-every-year-from-1922-now
A6: Nosferatu | B6: 1922 | C6: A | D6: Vampire Horror | E6: ☐ | F6: Genre Foundation | G6: https://www.bfi.org.uk/lists/10-great-german-expressionist-films
A7: Metropolis | B7: 1927 | C7: A | D7: Pre-1960 Foundation / Retro-Futurism / Dystopian Sci-Fi / Expressionism | E7: ☐ | F7: Genre Foundation | G7: https://www.bfi.org.uk/film/bda6ff8a-ed7e-5942-980d-c2910c0120ec/metropolis
A8: Dracula | B8: 1931 | C8: C | D8: Vampire Horror | E8: ☐ | F8: Canon Anchor | G8: https://www.bfi.org.uk/features/where-begin-universal-horror-cycle
A9: Frankenstein | B9: 1931 | C9: C | D9: Eco / Creature Horror | E9: ☐ | F9: Canon Anchor / Creature Feature | G9: https://www.bfi.org.uk/features/where-begin-universal-horror-cycle
A10: M | B10: 1931 | C10: A | D10: Pre-1960 Foundation / Crime / Proto-Noir / Serial Killer | E10: ☐ | F10: Genre Foundation | G10: https://www.bfi.org.uk/lists/10-great-german-films
A11: Freaks | B11: 1932 | C11: A | D11: Pre-1960 Foundation / Transgressive / Circus | E11: ☐ | F11: Cult Canon / Genre Foundation / Genre Essential / Banned / Controversial | G11: https://www.bfi.org.uk/lists/10-great-censored-films
A12: Vampyr | B12: 1932 | C12: A | D12: Vampire Horror | E12: ☐ | F12: Genre Foundation | G12: https://www.bfi.org.uk/lists/10-great-horror-films-1930s
A13: King Kong | B13: 1933 | C13: C | D13: Pre-1960 Anchor / Creature Feature / Adventure / Effects | E13: ☐ | F13: Canon Anchor / Practical FX Showcase / Creature Feature | G13: https://www.bfi.org.uk/features/king-kong-1933-10-things-know
... A43: The Tingler | B43: 1959 | C43: A | D43: Horror — Subgenre Review | E43: ☐ | F43: Genre Foundation | G43: https://www.bfi.org.uk/features/william-castle-cinema-gimmicks
D45: In collectie | E45: =COUNTIF(E2:E43,"☑")&" / "&COUNTA(A2:A43) -> 0 / 42

Sheet GUIDE
A1: CURATION GUIDE — Cult & Forgotten Cinema Master
A2: Doel: breed bewaren en beter organiseren — niet 'beste films ooit'. Slechte, bizarre en obscure films mogen juist blijven als hun cult-/preservationwaarde duidelijk is.
A4: Priority | B4: Betekenis | C4: Gebruik | D4: Master status | E4: Aantal | F4: Opmerking
A5: A | B5: Belangrijk voor de collectie | C5: Cultcanon, sterke preservation pick, genre-essential of uitzonderlijke oddity | D5: Totaal films | E5: 1917 | F5: Geen films verwijderd in deze curator-pass
A6: B | B6: Sterk interessant | C6: Deep cut, secundaire genre-entry, completion of interessante curiositeit | D6: Priority A | E6: 1081 | F6: Collectie-prioriteit, niet kwaliteitsrating
A7: C | B7: Context / anchor | C7: Grote mainstream/canonfilm die een stroming, stijl of genre helpt plaatsen | D7: Priority B | E7: 778 | F7: Sterke kandidaten / deep cuts
D8: Priority C | E8: 58 | F8: Context / anchors
D9: Genre review nodig | E9: 587 | F9: Bestaande masterdata was te generiek; titel blijft behouden
A10: Curator Tag | B10: Betekenis | D10: Search index | E10: 1917 | F10: Zoekt titel, jaar, genre, tags en source
A11: Cult Canon | B11: Defining cult title or established cult landmark.
A12: Canon Anchor | B12: Mainstream/major title kept as context for a movement or genre.
A13: VHS Classic | B13: Strong video-store / home-video identity.
A14: Rare VHS | B14: Scarcity or hard-to-find VHS history explicitly supported by existing notes.
A15: DTV Cult | B15: Direct-to-video title with cult/preservation value.
A16: SOV Cult | B16: Shot-on-video title with cult/preservation value.
A17: Grindhouse Favorite | B17: Strong grindhouse/exploitation circuit identity.
A18: Drive-In Classic | B18: Drive-in era staple or explicitly drive-in associated.
A19: Midnight Movie | B19: Midnight-movie / repertory cult identity.
A20: Notorious Flop | B20: Commercially notorious failure with lasting cult relevance.
A21: So-Bad-It's-Good | B21: Entertaining bad-movie reputation is part of the appeal.
A22: Camp Classic | B22: Camp value is central to the film's cult identity.
... A38: Needs Genre Review | B38: Kept in master, but genre data is still too generic.
A42: HORROR TAXONOMY — v23
A43: 'Horror' alleen is voortaan geen eindgenre. Waar de bestaande masterdata het ondersteunt, wordt horror uitgesplitst naar concrete subgenres. Onzekere gevallen blijven behouden als Horror — Subgenre Review.
A45: Subgenre | B45: Voorbeeld / bedoeling | C45: Aantal*
A46: Slasher / Proto-Slasher | B46: Masked/serial-killer slashers en voorlopers daarvan | C46: 32
A47: Body Horror | B47: Lichaamstransformatie, infectie, Cronenberg-achtige lichamelijkheid | C47: 23
A48: Supernatural / Occult | B48: Geesten, bovennatuurlijke dreiging, occultisme, satanisme | C48: 37
A49: Gothic Horror | B49: Hammer, kastelen, period gothic, klassieke monsters | C49: 18
A50: Psychological Horror | B50: Mentale ontwrichting, ambiguïteit, paranoia | C50: 15
A51: Zombie Horror | B51: Living dead / outbreak / zombie cinema | C51: 6
A52: Vampire Horror | B52: Vampierfilms, gothic of modern | C52: 13
A53: Folk Horror | B53: Ritueel, landschap, rurale folklore en occultisme | C53: 11
A54: Giallo | B54: Italiaanse murder-mystery/stylised horror-thrillers | C54: 7
A55: Sci-Fi Horror | B55: Sciencefiction die primair via horror werkt | C55: 32
A56: Found Footage | B56: Pseudo-recovered footage / faux-documentary horror | C56: 1
A57: Horror Comedy | B57: Horror waarin comedy structureel onderdeel is | C57: 30
... A60: Subgenre Review | B60: Nog te generiek in brondata; behouden, later handmatig verfijnen | C60: 62
A62: HIGH-CONCEPT FAMILY / VIDEO STORE CULT — v27
A63: VHS-era family/action/fantasy films built around a loud high-concept hook, recognizable star vehicle, creature/gadget gimmick or studio-B-movie premise. Cult value is based on memorability and video-store identity, not critical quality.
A65: Core trait | B65: Examples | C65: Curator use
A66: Star Vehicle | B66: Suburban Commando / Mr. Nanny / Kazaam | C66: Star Vehicle / Camp Classic
A67: High-Concept Hook | B67: Stay Tuned / Blank Check / House Arrest | C67: High-Concept / Video Store Cult
A68: Creature / Sci-Fi | B68: Spaced Invaders / Harry and the Hendersons | C68: Creature Feature / Video Store Cult
A69: Kids Action | B69: 3 Ninjas / Surf Ninjas / Sidekicks | C69: Forgotten Gem / Video Store Cult
A74: PSYCHOLOGICAL / SUBJECTIVE HORROR — v28
A75: Horror en horror-adjacent cinema waarin de werkelijkheid door een ontwrichte, onbetrouwbare of onder druk staande psyche wordt ervaren. Kernmotieven: hallucinatie, identiteitsverlies, paranoia, droomlogica, claustrofobische ruimtes en ambiguïteit tussen innerlijke en externe dreiging.
A77: Subgenre / lens | B77: Voorbeelden | C77: Wat onderscheidt het
A78: Subjective Horror | B78: Repulsion / Images / Symptoms | C78: We beleven de dreiging door een mogelijk onbetrouwbare waarneming
A79: Apartment Horror | B79: Repulsion / The Tenant / Rosemary's Baby | C79: Woonruimte wordt claustrofobisch en psychologisch vijandig
A80: Identity Horror | B80: Persona / Perfect Blue / Lost Highway | C80: Zelfbeeld, dubbelgangers en identiteit vallen uit elkaar
A81: Hallucinatory Horror | B81: Hour of the Wolf / Jacob's Ladder | C81: Visioenen en werkelijkheid zijn niet meer betrouwbaar te scheiden
A82: Psychological Surrealism | B82: 3 Women / Persona / The Cremator | C82: Droomlogica en symboliek nemen narratieve zekerheid over
A83: Gaslighting Horror | B83: The Entity / Rosemary's Baby | C83: De ervaring van het personage wordt systematisch betwijfeld of ontkend
A84: Urban Dread | B84: Cure / The Tenant / Repulsion | C84: De stad en alledaagse ruimtes worden vervreemdend en bedreigend
